[
  {
    "cp": {
      "identity": 284,
      "labels": [
        "ConnectionPoint",
        "GraphNode"
      ],
      "properties": {
        "LabelDelegations": "{\"2e3339c9-e627-4a0a-8b9c-c309e219984c\": {\"pool_id\": \"_\", \"labels\": {\"mac\": \"7c:f8:80:8e:4d:4d\", \"local_name\": \"TwentyFiveGigE0/0/0/18/1\"}}}",
        "Type": "TrunkPort",
        "GraphID": "13bccb17-1824-4941-a775-9b0a6db13cab",
        "CapacityDelegations": "{\"2e3339c9-e627-4a0a-8b9c-c309e219984c\": {\"pool_id\": \"_\", \"capacities\": {\"bw\": 25}}}",
        "StructuralInfo": "{\"adm_graph_ids\": [\"2e3339c9-e627-4a0a-8b9c-c309e219984c\", \"496d1550-9b00-4928-a5a6-61715037ba9c\"]}",
        "NodeID": "port+ucsd-data-sw:TwentyFiveGigE0/0/0/18/1",
        "Class": "ConnectionPoint",
        "Labels": "{\"local_name\": \"TwentyFiveGigE0/0/0/18/1\", \"mac\": \"7c:f8:80:8e:4d:4d\"}",
        "id": "561",
        "Capacities": "{\"bw\": 25}",
        "StitchNode": "false",
        "Name": "TwentyFiveGigE0/0/0/18/1"
      },
      "elementId": "284"
    }
  },
  {
    "cp": {
      "identity": 286,
      "labels": [
        "ConnectionPoint",
        "GraphNode"
      ],
      "properties": {
        "LabelDelegations": "{\"2e3339c9-e627-4a0a-8b9c-c309e219984c\": {\"pool_id\": \"_\", \"labels\": {\"mac\": \"7c:f8:80:8e:4d:4f\", \"local_name\": \"TwentyFiveGigE0/0/0/18/3\"}}}",
        "Type": "TrunkPort",
        "GraphID": "13bccb17-1824-4941-a775-9b0a6db13cab",
        "CapacityDelegations": "{\"2e3339c9-e627-4a0a-8b9c-c309e219984c\": {\"pool_id\": \"_\", \"capacities\": {\"bw\": 25}}}",
        "StructuralInfo": "{\"adm_graph_ids\": [\"2e3339c9-e627-4a0a-8b9c-c309e219984c\", \"496d1550-9b00-4928-a5a6-61715037ba9c\"]}",
        "NodeID": "port+ucsd-data-sw:TwentyFiveGigE0/0/0/18/3",
        "Class": "ConnectionPoint",
        "Labels": "{\"local_name\": \"TwentyFiveGigE0/0/0/18/3\", \"mac\": \"7c:f8:80:8e:4d:4f\"}",
        "id": "563",
        "Capacities": "{\"bw\": 25}",
        "StitchNode": "false",
        "Name": "TwentyFiveGigE0/0/0/18/3"
      },
      "elementId": "286"
    }
  },
  {
    "cp": {
      "identity": 285,
      "labels": [
        "ConnectionPoint",
        "GraphNode"
      ],
      "properties": {
        "LabelDelegations": "{\"2e3339c9-e627-4a0a-8b9c-c309e219984c\": {\"pool_id\": \"_\", \"labels\": {\"mac\": \"7c:f8:80:8e:4d:4e\", \"local_name\": \"TwentyFiveGigE0/0/0/18/2\"}}}",
        "Type": "TrunkPort",
        "GraphID": "13bccb17-1824-4941-a775-9b0a6db13cab",
        "CapacityDelegations": "{\"2e3339c9-e627-4a0a-8b9c-c309e219984c\": {\"pool_id\": \"_\", \"capacities\": {\"bw\": 25}}}",
        "StructuralInfo": "{\"adm_graph_ids\": [\"2e3339c9-e627-4a0a-8b9c-c309e219984c\", \"496d1550-9b00-4928-a5a6-61715037ba9c\"]}",
        "NodeID": "port+ucsd-data-sw:TwentyFiveGigE0/0/0/18/2",
        "Class": "ConnectionPoint",
        "Labels": "{\"local_name\": \"TwentyFiveGigE0/0/0/18/2\", \"mac\": \"7c:f8:80:8e:4d:4e\"}",
        "id": "562",
        "Capacities": "{\"bw\": 25}",
        "StitchNode": "false",
        "Name": "TwentyFiveGigE0/0/0/18/2"
      },
      "elementId": "285"
    }
  },
  {
    "cp": {
      "identity": 267,
      "labels": [
        "ConnectionPoint",
        "GraphNode"
      ],
      "properties": {
        "LabelDelegations": "{\"2e3339c9-e627-4a0a-8b9c-c309e219984c\": {\"pool_id\": \"_\", \"labels\": {\"mac\": \"7c:f8:80:8e:4d:38\", \"local_name\": \"HundredGigE0/0/0/13\"}}}",
        "Type": "TrunkPort",
        "GraphID": "13bccb17-1824-4941-a775-9b0a6db13cab",
        "CapacityDelegations": "{\"2e3339c9-e627-4a0a-8b9c-c309e219984c\": {\"pool_id\": \"_\", \"capacities\": {\"bw\": 100}}}",
        "StructuralInfo": "{\"adm_graph_ids\": [\"2e3339c9-e627-4a0a-8b9c-c309e219984c\", \"496d1550-9b00-4928-a5a6-61715037ba9c\"]}",
        "NodeID": "port+ucsd-data-sw:HundredGigE0/0/0/13",
        "Class": "ConnectionPoint",
        "Labels": "{\"local_name\": \"HundredGigE0/0/0/13\", \"mac\": \"7c:f8:80:8e:4d:38\"}",
        "id": "544",
        "Capacities": "{\"bw\": 100}",
        "StitchNode": "false",
        "Name": "HundredGigE0/0/0/13"
      },
      "elementId": "267"
    }
  },
  {
    "cp": {
      "identity": 272,
      "labels": [
        "ConnectionPoint",
        "GraphNode"
      ],
      "properties": {
        "LabelDelegations": "{\"2e3339c9-e627-4a0a-8b9c-c309e219984c\": {\"pool_id\": \"_\", \"labels\": {\"mac\": \"7c:f8:80:8e:4d:14\", \"local_name\": \"HundredGigE0/0/0/4\"}}}",
        "Type": "TrunkPort",
        "GraphID": "13bccb17-1824-4941-a775-9b0a6db13cab",
        "CapacityDelegations": "{\"2e3339c9-e627-4a0a-8b9c-c309e219984c\": {\"pool_id\": \"_\", \"capacities\": {\"bw\": 100}}}",
        "StructuralInfo": "{\"adm_graph_ids\": [\"2e3339c9-e627-4a0a-8b9c-c309e219984c\", \"496d1550-9b00-4928-a5a6-61715037ba9c\"]}",
        "NodeID": "port+ucsd-data-sw:HundredGigE0/0/0/4",
        "Class": "ConnectionPoint",
        "Labels": "{\"local_name\": \"HundredGigE0/0/0/4\", \"mac\": \"7c:f8:80:8e:4d:14\"}",
        "id": "549",
        "Capacities": "{\"bw\": 100}",
        "StitchNode": "false",
        "Name": "HundredGigE0/0/0/4"
      },
      "elementId": "272"
    }
  },
  {
    "cp": {
      "identity": 266,
      "labels": [
        "ConnectionPoint",
        "GraphNode"
      ],
      "properties": {
        "LabelDelegations": "{\"2e3339c9-e627-4a0a-8b9c-c309e219984c\": {\"pool_id\": \"_\", \"labels\": {\"mac\": \"7c:f8:80:8e:4d:30\", \"local_name\": \"HundredGigE0/0/0/11\"}}}",
        "Type": "TrunkPort",
        "GraphID": "13bccb17-1824-4941-a775-9b0a6db13cab",
        "CapacityDelegations": "{\"2e3339c9-e627-4a0a-8b9c-c309e219984c\": {\"pool_id\": \"_\", \"capacities\": {\"bw\": 100}}}",
        "StructuralInfo": "{\"adm_graph_ids\": [\"2e3339c9-e627-4a0a-8b9c-c309e219984c\", \"496d1550-9b00-4928-a5a6-61715037ba9c\"]}",
        "NodeID": "port+ucsd-data-sw:HundredGigE0/0/0/11",
        "Class": "ConnectionPoint",
        "Labels": "{\"local_name\": \"HundredGigE0/0/0/11\", \"mac\": \"7c:f8:80:8e:4d:30\"}",
        "id": "543",
        "Capacities": "{\"bw\": 100}",
        "StitchNode": "false",
        "Name": "HundredGigE0/0/0/11"
      },
      "elementId": "266"
    }
  },
  {
    "cp": {
      "identity": 268,
      "labels": [
        "ConnectionPoint",
        "GraphNode"
      ],
      "properties": {
        "LabelDelegations": "{\"2e3339c9-e627-4a0a-8b9c-c309e219984c\": {\"pool_id\": \"_\", \"labels\": {\"mac\": \"7c:f8:80:8e:4d:0c\", \"local_name\": \"HundredGigE0/0/0/2\"}}}",
        "Type": "TrunkPort",
        "GraphID": "13bccb17-1824-4941-a775-9b0a6db13cab",
        "CapacityDelegations": "{\"2e3339c9-e627-4a0a-8b9c-c309e219984c\": {\"pool_id\": \"_\", \"capacities\": {\"bw\": 100}}}",
        "StructuralInfo": "{\"adm_graph_ids\": [\"2e3339c9-e627-4a0a-8b9c-c309e219984c\", \"496d1550-9b00-4928-a5a6-61715037ba9c\"]}",
        "NodeID": "port+ucsd-data-sw:HundredGigE0/0/0/2",
        "Class": "ConnectionPoint",
        "Labels": "{\"local_name\": \"HundredGigE0/0/0/2\", \"mac\": \"7c:f8:80:8e:4d:0c\"}",
        "id": "545",
        "Capacities": "{\"bw\": 100}",
        "StitchNode": "false",
        "Name": "HundredGigE0/0/0/2"
      },
      "elementId": "268"
    }
  },
  {
    "cp": {
      "identity": 273,
      "labels": [
        "ConnectionPoint",
        "GraphNode"
      ],
      "properties": {
        "LabelDelegations": "{\"2e3339c9-e627-4a0a-8b9c-c309e219984c\": {\"pool_id\": \"_\", \"labels\": {\"mac\": \"7c:f8:80:8e:4d:18\", \"local_name\": \"HundredGigE0/0/0/5\"}}}",
        "Type": "TrunkPort",
        "GraphID": "13bccb17-1824-4941-a775-9b0a6db13cab",
        "CapacityDelegations": "{\"2e3339c9-e627-4a0a-8b9c-c309e219984c\": {\"pool_id\": \"_\", \"capacities\": {\"bw\": 100}}}",
        "StructuralInfo": "{\"adm_graph_ids\": [\"2e3339c9-e627-4a0a-8b9c-c309e219984c\", \"496d1550-9b00-4928-a5a6-61715037ba9c\"]}",
        "NodeID": "port+ucsd-data-sw:HundredGigE0/0/0/5",
        "Class": "ConnectionPoint",
        "Labels": "{\"local_name\": \"HundredGigE0/0/0/5\", \"mac\": \"7c:f8:80:8e:4d:18\"}",
        "id": "550",
        "Capacities": "{\"bw\": 100}",
        "StitchNode": "false",
        "Name": "HundredGigE0/0/0/5"
      },
      "elementId": "273"
    }
  },
  {
    "cp": {
      "identity": 283,
      "labels": [
        "ConnectionPoint",
        "GraphNode"
      ],
      "properties": {
        "LabelDelegations": "{\"2e3339c9-e627-4a0a-8b9c-c309e219984c\": {\"pool_id\": \"_\", \"labels\": {\"mac\": \"7c:f8:80:8e:4d:4c\", \"local_name\": \"TwentyFiveGigE0/0/0/18/0\"}}}",
        "Type": "TrunkPort",
        "GraphID": "13bccb17-1824-4941-a775-9b0a6db13cab",
        "CapacityDelegations": "{\"2e3339c9-e627-4a0a-8b9c-c309e219984c\": {\"pool_id\": \"_\", \"capacities\": {\"bw\": 25}}}",
        "StructuralInfo": "{\"adm_graph_ids\": [\"2e3339c9-e627-4a0a-8b9c-c309e219984c\", \"496d1550-9b00-4928-a5a6-61715037ba9c\"]}",
        "NodeID": "port+ucsd-data-sw:TwentyFiveGigE0/0/0/18/0",
        "Class": "ConnectionPoint",
        "Labels": "{\"local_name\": \"TwentyFiveGigE0/0/0/18/0\", \"mac\": \"7c:f8:80:8e:4d:4c\"}",
        "id": "560",
        "Capacities": "{\"bw\": 25}",
        "StitchNode": "false",
        "Name": "TwentyFiveGigE0/0/0/18/0"
      },
      "elementId": "283"
    }
  },
  {
    "cp": {
      "identity": 277,
      "labels": [
        "ConnectionPoint",
        "GraphNode"
      ],
      "properties": {
        "LabelDelegations": "{\"2e3339c9-e627-4a0a-8b9c-c309e219984c\": {\"pool_id\": \"_\", \"labels\": {\"mac\": \"7c:f8:80:8e:4d:20\", \"local_name\": \"HundredGigE0/0/0/7\"}}}",
        "Type": "TrunkPort",
        "GraphID": "13bccb17-1824-4941-a775-9b0a6db13cab",
        "CapacityDelegations": "{\"2e3339c9-e627-4a0a-8b9c-c309e219984c\": {\"pool_id\": \"_\", \"capacities\": {\"bw\": 100}}}",
        "StructuralInfo": "{\"adm_graph_ids\": [\"2e3339c9-e627-4a0a-8b9c-c309e219984c\", \"496d1550-9b00-4928-a5a6-61715037ba9c\"]}",
        "NodeID": "port+ucsd-data-sw:HundredGigE0/0/0/7",
        "Class": "ConnectionPoint",
        "Labels": "{\"local_name\": \"HundredGigE0/0/0/7\", \"mac\": \"7c:f8:80:8e:4d:20\"}",
        "id": "554",
        "Capacities": "{\"bw\": 100}",
        "StitchNode": "false",
        "Name": "HundredGigE0/0/0/7"
      },
      "elementId": "277"
    }
  },
  {
    "cp": {
      "identity": 276,
      "labels": [
        "ConnectionPoint",
        "GraphNode"
      ],
      "properties": {
        "LabelDelegations": "{\"2e3339c9-e627-4a0a-8b9c-c309e219984c\": {\"pool_id\": \"_\", \"labels\": {\"mac\": \"7c:f8:80:8e:4d:1c\", \"local_name\": \"HundredGigE0/0/0/6\"}}}",
        "Type": "TrunkPort",
        "GraphID": "13bccb17-1824-4941-a775-9b0a6db13cab",
        "CapacityDelegations": "{\"2e3339c9-e627-4a0a-8b9c-c309e219984c\": {\"pool_id\": \"_\", \"capacities\": {\"bw\": 100}}}",
        "StructuralInfo": "{\"adm_graph_ids\": [\"2e3339c9-e627-4a0a-8b9c-c309e219984c\", \"496d1550-9b00-4928-a5a6-61715037ba9c\"]}",
        "NodeID": "port+ucsd-data-sw:HundredGigE0/0/0/6",
        "Class": "ConnectionPoint",
        "Labels": "{\"local_name\": \"HundredGigE0/0/0/6\", \"mac\": \"7c:f8:80:8e:4d:1c\"}",
        "id": "553",
        "Capacities": "{\"bw\": 100}",
        "StitchNode": "false",
        "Name": "HundredGigE0/0/0/6"
      },
      "elementId": "276"
    }
  },
  {
    "cp": {
      "identity": 264,
      "labels": [
        "ConnectionPoint",
        "GraphNode"
      ],
      "properties": {
        "LabelDelegations": "{\"2e3339c9-e627-4a0a-8b9c-c309e219984c\": {\"pool_id\": \"_\", \"labels\": {\"mac\": \"7c:f8:80:8e:4d:04\", \"local_name\": \"HundredGigE0/0/0/0\"}}}",
        "Type": "TrunkPort",
        "GraphID": "13bccb17-1824-4941-a775-9b0a6db13cab",
        "CapacityDelegations": "{\"2e3339c9-e627-4a0a-8b9c-c309e219984c\": {\"pool_id\": \"_\", \"capacities\": {\"bw\": 100}}}",
        "StructuralInfo": "{\"adm_graph_ids\": [\"2e3339c9-e627-4a0a-8b9c-c309e219984c\", \"496d1550-9b00-4928-a5a6-61715037ba9c\"]}",
        "NodeID": "port+ucsd-data-sw:HundredGigE0/0/0/0",
        "Class": "ConnectionPoint",
        "Labels": "{\"local_name\": \"HundredGigE0/0/0/0\", \"mac\": \"7c:f8:80:8e:4d:04\"}",
        "id": "541",
        "Capacities": "{\"bw\": 100}",
        "StitchNode": "false",
        "Name": "HundredGigE0/0/0/0"
      },
      "elementId": "264"
    }
  },
  {
    "cp": {
      "identity": 280,
      "labels": [
        "ConnectionPoint",
        "GraphNode"
      ],
      "properties": {
        "LabelDelegations": "{\"2e3339c9-e627-4a0a-8b9c-c309e219984c\": {\"pool_id\": \"_\", \"labels\": {\"mac\": \"7c:f8:80:8e:4d:45\", \"local_name\": \"TwentyFiveGigE0/0/0/16/1\"}}}",
        "Type": "TrunkPort",
        "GraphID": "13bccb17-1824-4941-a775-9b0a6db13cab",
        "CapacityDelegations": "{\"2e3339c9-e627-4a0a-8b9c-c309e219984c\": {\"pool_id\": \"_\", \"capacities\": {\"bw\": 25}}}",
        "StructuralInfo": "{\"adm_graph_ids\": [\"2e3339c9-e627-4a0a-8b9c-c309e219984c\", \"496d1550-9b00-4928-a5a6-61715037ba9c\"]}",
        "NodeID": "port+ucsd-data-sw:TwentyFiveGigE0/0/0/16/1",
        "Class": "ConnectionPoint",
        "Labels": "{\"local_name\": \"TwentyFiveGigE0/0/0/16/1\", \"mac\": \"7c:f8:80:8e:4d:45\"}",
        "id": "557",
        "Capacities": "{\"bw\": 25}",
        "StitchNode": "false",
        "Name": "TwentyFiveGigE0/0/0/16/1"
      },
      "elementId": "280"
    }
  },
  {
    "cp": {
      "identity": 282,
      "labels": [
        "ConnectionPoint",
        "GraphNode"
      ],
      "properties": {
        "LabelDelegations": "{\"2e3339c9-e627-4a0a-8b9c-c309e219984c\": {\"pool_id\": \"_\", \"labels\": {\"mac\": \"7c:f8:80:8e:4d:47\", \"local_name\": \"TwentyFiveGigE0/0/0/16/3\"}}}",
        "Type": "TrunkPort",
        "GraphID": "13bccb17-1824-4941-a775-9b0a6db13cab",
        "CapacityDelegations": "{\"2e3339c9-e627-4a0a-8b9c-c309e219984c\": {\"pool_id\": \"_\", \"capacities\": {\"bw\": 25}}}",
        "StructuralInfo": "{\"adm_graph_ids\": [\"2e3339c9-e627-4a0a-8b9c-c309e219984c\", \"496d1550-9b00-4928-a5a6-61715037ba9c\"]}",
        "NodeID": "port+ucsd-data-sw:TwentyFiveGigE0/0/0/16/3",
        "Class": "ConnectionPoint",
        "Labels": "{\"local_name\": \"TwentyFiveGigE0/0/0/16/3\", \"mac\": \"7c:f8:80:8e:4d:47\"}",
        "id": "559",
        "Capacities": "{\"bw\": 25}",
        "StitchNode": "false",
        "Name": "TwentyFiveGigE0/0/0/16/3"
      },
      "elementId": "282"
    }
  },
  {
    "cp": {
      "identity": 278,
      "labels": [
        "ConnectionPoint",
        "GraphNode"
      ],
      "properties": {
        "LabelDelegations": "{\"2e3339c9-e627-4a0a-8b9c-c309e219984c\": {\"pool_id\": \"_\", \"labels\": {\"mac\": \"7c:f8:80:8e:4d:28\", \"local_name\": \"HundredGigE0/0/0/9\"}}}",
        "Type": "TrunkPort",
        "GraphID": "13bccb17-1824-4941-a775-9b0a6db13cab",
        "CapacityDelegations": "{\"2e3339c9-e627-4a0a-8b9c-c309e219984c\": {\"pool_id\": \"_\", \"capacities\": {\"bw\": 100}}}",
        "StructuralInfo": "{\"adm_graph_ids\": [\"2e3339c9-e627-4a0a-8b9c-c309e219984c\", \"496d1550-9b00-4928-a5a6-61715037ba9c\"]}",
        "NodeID": "port+ucsd-data-sw:HundredGigE0/0/0/9",
        "Class": "ConnectionPoint",
        "Labels": "{\"local_name\": \"HundredGigE0/0/0/9\", \"mac\": \"7c:f8:80:8e:4d:28\"}",
        "id": "555",
        "Capacities": "{\"bw\": 100}",
        "StitchNode": "false",
        "Name": "HundredGigE0/0/0/9"
      },
      "elementId": "278"
    }
  },
  {
    "cp": {
      "identity": 279,
      "labels": [
        "ConnectionPoint",
        "GraphNode"
      ],
      "properties": {
        "LabelDelegations": "{\"2e3339c9-e627-4a0a-8b9c-c309e219984c\": {\"pool_id\": \"_\", \"labels\": {\"mac\": \"7c:f8:80:8e:4d:44\", \"local_name\": \"TwentyFiveGigE0/0/0/16/0\"}}}",
        "Type": "TrunkPort",
        "GraphID": "13bccb17-1824-4941-a775-9b0a6db13cab",
        "CapacityDelegations": "{\"2e3339c9-e627-4a0a-8b9c-c309e219984c\": {\"pool_id\": \"_\", \"capacities\": {\"bw\": 25}}}",
        "StructuralInfo": "{\"adm_graph_ids\": [\"2e3339c9-e627-4a0a-8b9c-c309e219984c\", \"496d1550-9b00-4928-a5a6-61715037ba9c\"]}",
        "NodeID": "port+ucsd-data-sw:TwentyFiveGigE0/0/0/16/0",
        "Class": "ConnectionPoint",
        "Labels": "{\"local_name\": \"TwentyFiveGigE0/0/0/16/0\", \"mac\": \"7c:f8:80:8e:4d:44\"}",
        "id": "556",
        "Capacities": "{\"bw\": 25}",
        "StitchNode": "false",
        "Name": "TwentyFiveGigE0/0/0/16/0"
      },
      "elementId": "279"
    }
  },
  {
    "cp": {
      "identity": 281,
      "labels": [
        "ConnectionPoint",
        "GraphNode"
      ],
      "properties": {
        "LabelDelegations": "{\"2e3339c9-e627-4a0a-8b9c-c309e219984c\": {\"pool_id\": \"_\", \"labels\": {\"mac\": \"7c:f8:80:8e:4d:46\", \"local_name\": \"TwentyFiveGigE0/0/0/16/2\"}}}",
        "Type": "TrunkPort",
        "GraphID": "13bccb17-1824-4941-a775-9b0a6db13cab",
        "CapacityDelegations": "{\"2e3339c9-e627-4a0a-8b9c-c309e219984c\": {\"pool_id\": \"_\", \"capacities\": {\"bw\": 25}}}",
        "StructuralInfo": "{\"adm_graph_ids\": [\"2e3339c9-e627-4a0a-8b9c-c309e219984c\", \"496d1550-9b00-4928-a5a6-61715037ba9c\"]}",
        "NodeID": "port+ucsd-data-sw:TwentyFiveGigE0/0/0/16/2",
        "Class": "ConnectionPoint",
        "Labels": "{\"local_name\": \"TwentyFiveGigE0/0/0/16/2\", \"mac\": \"7c:f8:80:8e:4d:46\"}",
        "id": "558",
        "Capacities": "{\"bw\": 25}",
        "StitchNode": "false",
        "Name": "TwentyFiveGigE0/0/0/16/2"
      },
      "elementId": "281"
    }
  },
  {
    "cp": {
      "identity": 270,
      "labels": [
        "ConnectionPoint",
        "GraphNode"
      ],
      "properties": {
        "LabelDelegations": "{\"2e3339c9-e627-4a0a-8b9c-c309e219984c\": {\"pool_id\": \"_\", \"labels\": {\"mac\": \"7c:f8:80:8e:4d:5c\", \"ipv4\": \"10.132.0.154\", \"ipv6\": \"2602:fcfb:8:1024::1a\", \"local_name\": \"HundredGigE0/0/0/22.3100\"}}}",
        "Type": "TrunkPort",
        "GraphID": "13bccb17-1824-4941-a775-9b0a6db13cab",
        "CapacityDelegations": "{\"2e3339c9-e627-4a0a-8b9c-c309e219984c\": {\"pool_id\": \"_\", \"capacities\": {\"bw\": 100}}}",
        "StructuralInfo": "{\"adm_graph_ids\": [\"2e3339c9-e627-4a0a-8b9c-c309e219984c\"]}",
        "NodeID": "port+ucsd-data-sw:HundredGigE0/0/0/22.3100",
        "Class": "ConnectionPoint",
        "Labels": "{\"ipv4\": \"10.132.0.154\", \"ipv6\": \"2602:fcfb:8:1024::1a\", \"local_name\": \"HundredGigE0/0/0/22.3100\", \"mac\": \"7c:f8:80:8e:4d:5c\"}",
        "id": "547",
        "Capacities": "{\"bw\": 100}",
        "StitchNode": "false",
        "Name": "HundredGigE0/0/0/22.3100"
      },
      "elementId": "270"
    }
  },
  {
    "cp": {
      "identity": 2336,
      "labels": [
        "ConnectionPoint",
        "GraphNode"
      ],
      "properties": {
        "LabelDelegations": "{\"2e3339c9-e627-4a0a-8b9c-c309e219984c\": {\"pool_id\": \"_\", \"labels\": {\"mac\": \"7c:f8:80:8e:4d:4c\", \"local_name\": \"TwentyFiveGigE0/0/0/18/0\"}}}",
        "Type": "TrunkPort",
        "GraphID": "13bccb17-1824-4941-a775-9b0a6db13cab",
        "CapacityDelegations": "{\"2e3339c9-e627-4a0a-8b9c-c309e219984c\": {\"pool_id\": \"_\", \"capacities\": {\"bw\": 25}}}",
        "StructuralInfo": "{\"adm_graph_ids\": [\"2e3339c9-e627-4a0a-8b9c-c309e219984c\", \"496d1550-9b00-4928-a5a6-61715037ba9c\"]}",
        "NodeID": "port+ucsd-data-sw:TwentyFiveGigE0/0/0/18/0",
        "Class": "ConnectionPoint",
        "Labels": "{\"local_name\": \"TwentyFiveGigE0/0/0/18/0\", \"mac\": \"7c:f8:80:8e:4d:4c\"}",
        "id": "560",
        "Capacities": "{\"bw\": 25}",
        "StitchNode": "false",
        "Name": "TwentyFiveGigE0/0/0/18/0"
      },
      "elementId": "2336"
    }
  },
  {
    "cp": {
      "identity": 2319,
      "labels": [
        "ConnectionPoint",
        "GraphNode"
      ],
      "properties": {
        "LabelDelegations": "{\"2e3339c9-e627-4a0a-8b9c-c309e219984c\": {\"pool_id\": \"_\", \"labels\": {\"mac\": \"7c:f8:80:8e:4d:30\", \"local_name\": \"HundredGigE0/0/0/11\"}}}",
        "Type": "TrunkPort",
        "GraphID": "13bccb17-1824-4941-a775-9b0a6db13cab",
        "CapacityDelegations": "{\"2e3339c9-e627-4a0a-8b9c-c309e219984c\": {\"pool_id\": \"_\", \"capacities\": {\"bw\": 100}}}",
        "StructuralInfo": "{\"adm_graph_ids\": [\"2e3339c9-e627-4a0a-8b9c-c309e219984c\", \"496d1550-9b00-4928-a5a6-61715037ba9c\"]}",
        "NodeID": "port+ucsd-data-sw:HundredGigE0/0/0/11",
        "Class": "ConnectionPoint",
        "Labels": "{\"local_name\": \"HundredGigE0/0/0/11\", \"mac\": \"7c:f8:80:8e:4d:30\"}",
        "id": "543",
        "Capacities": "{\"bw\": 100}",
        "StitchNode": "false",
        "Name": "HundredGigE0/0/0/11"
      },
      "elementId": "2319"
    }
  },
  {
    "cp": {
      "identity": 2329,
      "labels": [
        "ConnectionPoint",
        "GraphNode"
      ],
      "properties": {
        "LabelDelegations": "{\"2e3339c9-e627-4a0a-8b9c-c309e219984c\": {\"pool_id\": \"_\", \"labels\": {\"mac\": \"7c:f8:80:8e:4d:1c\", \"local_name\": \"HundredGigE0/0/0/6\"}}}",
        "Type": "TrunkPort",
        "GraphID": "13bccb17-1824-4941-a775-9b0a6db13cab",
        "CapacityDelegations": "{\"2e3339c9-e627-4a0a-8b9c-c309e219984c\": {\"pool_id\": \"_\", \"capacities\": {\"bw\": 100}}}",
        "StructuralInfo": "{\"adm_graph_ids\": [\"2e3339c9-e627-4a0a-8b9c-c309e219984c\", \"496d1550-9b00-4928-a5a6-61715037ba9c\"]}",
        "NodeID": "port+ucsd-data-sw:HundredGigE0/0/0/6",
        "Class": "ConnectionPoint",
        "Labels": "{\"local_name\": \"HundredGigE0/0/0/6\", \"mac\": \"7c:f8:80:8e:4d:1c\"}",
        "id": "553",
        "Capacities": "{\"bw\": 100}",
        "StitchNode": "false",
        "Name": "HundredGigE0/0/0/6"
      },
      "elementId": "2329"
    }
  },
  {
    "cp": {
      "identity": 2320,
      "labels": [
        "ConnectionPoint",
        "GraphNode"
      ],
      "properties": {
        "LabelDelegations": "{\"2e3339c9-e627-4a0a-8b9c-c309e219984c\": {\"pool_id\": \"_\", \"labels\": {\"mac\": \"7c:f8:80:8e:4d:38\", \"local_name\": \"HundredGigE0/0/0/13\"}}}",
        "Type": "TrunkPort",
        "GraphID": "13bccb17-1824-4941-a775-9b0a6db13cab",
        "CapacityDelegations": "{\"2e3339c9-e627-4a0a-8b9c-c309e219984c\": {\"pool_id\": \"_\", \"capacities\": {\"bw\": 100}}}",
        "StructuralInfo": "{\"adm_graph_ids\": [\"2e3339c9-e627-4a0a-8b9c-c309e219984c\", \"496d1550-9b00-4928-a5a6-61715037ba9c\"]}",
        "NodeID": "port+ucsd-data-sw:HundredGigE0/0/0/13",
        "Class": "ConnectionPoint",
        "Labels": "{\"local_name\": \"HundredGigE0/0/0/13\", \"mac\": \"7c:f8:80:8e:4d:38\"}",
        "id": "544",
        "Capacities": "{\"bw\": 100}",
        "StitchNode": "false",
        "Name": "HundredGigE0/0/0/13"
      },
      "elementId": "2320"
    }
  },
  {
    "cp": {
      "identity": 2339,
      "labels": [
        "ConnectionPoint",
        "GraphNode"
      ],
      "properties": {
        "LabelDelegations": "{\"2e3339c9-e627-4a0a-8b9c-c309e219984c\": {\"pool_id\": \"_\", \"labels\": {\"mac\": \"7c:f8:80:8e:4d:4f\", \"local_name\": \"TwentyFiveGigE0/0/0/18/3\"}}}",
        "Type": "TrunkPort",
        "GraphID": "13bccb17-1824-4941-a775-9b0a6db13cab",
        "CapacityDelegations": "{\"2e3339c9-e627-4a0a-8b9c-c309e219984c\": {\"pool_id\": \"_\", \"capacities\": {\"bw\": 25}}}",
        "StructuralInfo": "{\"adm_graph_ids\": [\"2e3339c9-e627-4a0a-8b9c-c309e219984c\", \"496d1550-9b00-4928-a5a6-61715037ba9c\"]}",
        "NodeID": "port+ucsd-data-sw:TwentyFiveGigE0/0/0/18/3",
        "Class": "ConnectionPoint",
        "Labels": "{\"local_name\": \"TwentyFiveGigE0/0/0/18/3\", \"mac\": \"7c:f8:80:8e:4d:4f\"}",
        "id": "563",
        "Capacities": "{\"bw\": 25}",
        "StitchNode": "false",
        "Name": "TwentyFiveGigE0/0/0/18/3"
      },
      "elementId": "2339"
    }
  },
  {
    "cp": {
      "identity": 2330,
      "labels": [
        "ConnectionPoint",
        "GraphNode"
      ],
      "properties": {
        "LabelDelegations": "{\"2e3339c9-e627-4a0a-8b9c-c309e219984c\": {\"pool_id\": \"_\", \"labels\": {\"mac\": \"7c:f8:80:8e:4d:20\", \"local_name\": \"HundredGigE0/0/0/7\"}}}",
        "Type": "TrunkPort",
        "GraphID": "13bccb17-1824-4941-a775-9b0a6db13cab",
        "CapacityDelegations": "{\"2e3339c9-e627-4a0a-8b9c-c309e219984c\": {\"pool_id\": \"_\", \"capacities\": {\"bw\": 100}}}",
        "StructuralInfo": "{\"adm_graph_ids\": [\"2e3339c9-e627-4a0a-8b9c-c309e219984c\", \"496d1550-9b00-4928-a5a6-61715037ba9c\"]}",
        "NodeID": "port+ucsd-data-sw:HundredGigE0/0/0/7",
        "Class": "ConnectionPoint",
        "Labels": "{\"local_name\": \"HundredGigE0/0/0/7\", \"mac\": \"7c:f8:80:8e:4d:20\"}",
        "id": "554",
        "Capacities": "{\"bw\": 100}",
        "StitchNode": "false",
        "Name": "HundredGigE0/0/0/7"
      },
      "elementId": "2330"
    }
  },
  {
    "cp": {
      "identity": 2332,
      "labels": [
        "ConnectionPoint",
        "GraphNode"
      ],
      "properties": {
        "LabelDelegations": "{\"2e3339c9-e627-4a0a-8b9c-c309e219984c\": {\"pool_id\": \"_\", \"labels\": {\"mac\": \"7c:f8:80:8e:4d:44\", \"local_name\": \"TwentyFiveGigE0/0/0/16/0\"}}}",
        "Type": "TrunkPort",
        "GraphID": "13bccb17-1824-4941-a775-9b0a6db13cab",
        "CapacityDelegations": "{\"2e3339c9-e627-4a0a-8b9c-c309e219984c\": {\"pool_id\": \"_\", \"capacities\": {\"bw\": 25}}}",
        "StructuralInfo": "{\"adm_graph_ids\": [\"2e3339c9-e627-4a0a-8b9c-c309e219984c\", \"496d1550-9b00-4928-a5a6-61715037ba9c\"]}",
        "NodeID": "port+ucsd-data-sw:TwentyFiveGigE0/0/0/16/0",
        "Class": "ConnectionPoint",
        "Labels": "{\"local_name\": \"TwentyFiveGigE0/0/0/16/0\", \"mac\": \"7c:f8:80:8e:4d:44\"}",
        "id": "556",
        "Capacities": "{\"bw\": 25}",
        "StitchNode": "false",
        "Name": "TwentyFiveGigE0/0/0/16/0"
      },
      "elementId": "2332"
    }
  },
  {
    "cp": {
      "identity": 2335,
      "labels": [
        "ConnectionPoint",
        "GraphNode"
      ],
      "properties": {
        "LabelDelegations": "{\"2e3339c9-e627-4a0a-8b9c-c309e219984c\": {\"pool_id\": \"_\", \"labels\": {\"mac\": \"7c:f8:80:8e:4d:47\", \"local_name\": \"TwentyFiveGigE0/0/0/16/3\"}}}",
        "Type": "TrunkPort",
        "GraphID": "13bccb17-1824-4941-a775-9b0a6db13cab",
        "CapacityDelegations": "{\"2e3339c9-e627-4a0a-8b9c-c309e219984c\": {\"pool_id\": \"_\", \"capacities\": {\"bw\": 25}}}",
        "StructuralInfo": "{\"adm_graph_ids\": [\"2e3339c9-e627-4a0a-8b9c-c309e219984c\", \"496d1550-9b00-4928-a5a6-61715037ba9c\"]}",
        "NodeID": "port+ucsd-data-sw:TwentyFiveGigE0/0/0/16/3",
        "Class": "ConnectionPoint",
        "Labels": "{\"local_name\": \"TwentyFiveGigE0/0/0/16/3\", \"mac\": \"7c:f8:80:8e:4d:47\"}",
        "id": "559",
        "Capacities": "{\"bw\": 25}",
        "StitchNode": "false",
        "Name": "TwentyFiveGigE0/0/0/16/3"
      },
      "elementId": "2335"
    }
  },
  {
    "cp": {
      "identity": 2323,
      "labels": [
        "ConnectionPoint",
        "GraphNode"
      ],
      "properties": {
        "LabelDelegations": "{\"2e3339c9-e627-4a0a-8b9c-c309e219984c\": {\"pool_id\": \"_\", \"labels\": {\"mac\": \"7c:f8:80:8e:4d:5c\", \"ipv4\": \"10.132.0.154\", \"ipv6\": \"2602:fcfb:8:1024::1a\", \"local_name\": \"HundredGigE0/0/0/22.3100\"}}}",
        "Type": "TrunkPort",
        "GraphID": "13bccb17-1824-4941-a775-9b0a6db13cab",
        "CapacityDelegations": "{\"2e3339c9-e627-4a0a-8b9c-c309e219984c\": {\"pool_id\": \"_\", \"capacities\": {\"bw\": 100}}}",
        "StructuralInfo": "{\"adm_graph_ids\": [\"2e3339c9-e627-4a0a-8b9c-c309e219984c\"]}",
        "NodeID": "port+ucsd-data-sw:HundredGigE0/0/0/22.3100",
        "Class": "ConnectionPoint",
        "Labels": "{\"ipv4\": \"10.132.0.154\", \"ipv6\": \"2602:fcfb:8:1024::1a\", \"local_name\": \"HundredGigE0/0/0/22.3100\", \"mac\": \"7c:f8:80:8e:4d:5c\"}",
        "id": "547",
        "Capacities": "{\"bw\": 100}",
        "StitchNode": "false",
        "Name": "HundredGigE0/0/0/22.3100"
      },
      "elementId": "2323"
    }
  },
  {
    "cp": {
      "identity": 2331,
      "labels": [
        "ConnectionPoint",
        "GraphNode"
      ],
      "properties": {
        "LabelDelegations": "{\"2e3339c9-e627-4a0a-8b9c-c309e219984c\": {\"pool_id\": \"_\", \"labels\": {\"mac\": \"7c:f8:80:8e:4d:28\", \"local_name\": \"HundredGigE0/0/0/9\"}}}",
        "Type": "TrunkPort",
        "GraphID": "13bccb17-1824-4941-a775-9b0a6db13cab",
        "CapacityDelegations": "{\"2e3339c9-e627-4a0a-8b9c-c309e219984c\": {\"pool_id\": \"_\", \"capacities\": {\"bw\": 100}}}",
        "StructuralInfo": "{\"adm_graph_ids\": [\"2e3339c9-e627-4a0a-8b9c-c309e219984c\", \"496d1550-9b00-4928-a5a6-61715037ba9c\"]}",
        "NodeID": "port+ucsd-data-sw:HundredGigE0/0/0/9",
        "Class": "ConnectionPoint",
        "Labels": "{\"local_name\": \"HundredGigE0/0/0/9\", \"mac\": \"7c:f8:80:8e:4d:28\"}",
        "id": "555",
        "Capacities": "{\"bw\": 100}",
        "StitchNode": "false",
        "Name": "HundredGigE0/0/0/9"
      },
      "elementId": "2331"
    }
  },
  {
    "cp": {
      "identity": 2334,
      "labels": [
        "ConnectionPoint",
        "GraphNode"
      ],
      "properties": {
        "LabelDelegations": "{\"2e3339c9-e627-4a0a-8b9c-c309e219984c\": {\"pool_id\": \"_\", \"labels\": {\"mac\": \"7c:f8:80:8e:4d:46\", \"local_name\": \"TwentyFiveGigE0/0/0/16/2\"}}}",
        "Type": "TrunkPort",
        "GraphID": "13bccb17-1824-4941-a775-9b0a6db13cab",
        "CapacityDelegations": "{\"2e3339c9-e627-4a0a-8b9c-c309e219984c\": {\"pool_id\": \"_\", \"capacities\": {\"bw\": 25}}}",
        "StructuralInfo": "{\"adm_graph_ids\": [\"2e3339c9-e627-4a0a-8b9c-c309e219984c\", \"496d1550-9b00-4928-a5a6-61715037ba9c\"]}",
        "NodeID": "port+ucsd-data-sw:TwentyFiveGigE0/0/0/16/2",
        "Class": "ConnectionPoint",
        "Labels": "{\"local_name\": \"TwentyFiveGigE0/0/0/16/2\", \"mac\": \"7c:f8:80:8e:4d:46\"}",
        "id": "558",
        "Capacities": "{\"bw\": 25}",
        "StitchNode": "false",
        "Name": "TwentyFiveGigE0/0/0/16/2"
      },
      "elementId": "2334"
    }
  },
  {
    "cp": {
      "identity": 2333,
      "labels": [
        "ConnectionPoint",
        "GraphNode"
      ],
      "properties": {
        "LabelDelegations": "{\"2e3339c9-e627-4a0a-8b9c-c309e219984c\": {\"pool_id\": \"_\", \"labels\": {\"mac\": \"7c:f8:80:8e:4d:45\", \"local_name\": \"TwentyFiveGigE0/0/0/16/1\"}}}",
        "Type": "TrunkPort",
        "GraphID": "13bccb17-1824-4941-a775-9b0a6db13cab",
        "CapacityDelegations": "{\"2e3339c9-e627-4a0a-8b9c-c309e219984c\": {\"pool_id\": \"_\", \"capacities\": {\"bw\": 25}}}",
        "StructuralInfo": "{\"adm_graph_ids\": [\"2e3339c9-e627-4a0a-8b9c-c309e219984c\", \"496d1550-9b00-4928-a5a6-61715037ba9c\"]}",
        "NodeID": "port+ucsd-data-sw:TwentyFiveGigE0/0/0/16/1",
        "Class": "ConnectionPoint",
        "Labels": "{\"local_name\": \"TwentyFiveGigE0/0/0/16/1\", \"mac\": \"7c:f8:80:8e:4d:45\"}",
        "id": "557",
        "Capacities": "{\"bw\": 25}",
        "StitchNode": "false",
        "Name": "TwentyFiveGigE0/0/0/16/1"
      },
      "elementId": "2333"
    }
  },
  {
    "cp": {
      "identity": 2325,
      "labels": [
        "ConnectionPoint",
        "GraphNode"
      ],
      "properties": {
        "LabelDelegations": "{\"2e3339c9-e627-4a0a-8b9c-c309e219984c\": {\"pool_id\": \"_\", \"labels\": {\"mac\": \"7c:f8:80:8e:4d:14\", \"local_name\": \"HundredGigE0/0/0/4\"}}}",
        "Type": "TrunkPort",
        "GraphID": "13bccb17-1824-4941-a775-9b0a6db13cab",
        "CapacityDelegations": "{\"2e3339c9-e627-4a0a-8b9c-c309e219984c\": {\"pool_id\": \"_\", \"capacities\": {\"bw\": 100}}}",
        "StructuralInfo": "{\"adm_graph_ids\": [\"2e3339c9-e627-4a0a-8b9c-c309e219984c\", \"496d1550-9b00-4928-a5a6-61715037ba9c\"]}",
        "NodeID": "port+ucsd-data-sw:HundredGigE0/0/0/4",
        "Class": "ConnectionPoint",
        "Labels": "{\"local_name\": \"HundredGigE0/0/0/4\", \"mac\": \"7c:f8:80:8e:4d:14\"}",
        "id": "549",
        "Capacities": "{\"bw\": 100}",
        "StitchNode": "false",
        "Name": "HundredGigE0/0/0/4"
      },
      "elementId": "2325"
    }
  },
  {
    "cp": {
      "identity": 2337,
      "labels": [
        "ConnectionPoint",
        "GraphNode"
      ],
      "properties": {
        "LabelDelegations": "{\"2e3339c9-e627-4a0a-8b9c-c309e219984c\": {\"pool_id\": \"_\", \"labels\": {\"mac\": \"7c:f8:80:8e:4d:4d\", \"local_name\": \"TwentyFiveGigE0/0/0/18/1\"}}}",
        "Type": "TrunkPort",
        "GraphID": "13bccb17-1824-4941-a775-9b0a6db13cab",
        "CapacityDelegations": "{\"2e3339c9-e627-4a0a-8b9c-c309e219984c\": {\"pool_id\": \"_\", \"capacities\": {\"bw\": 25}}}",
        "StructuralInfo": "{\"adm_graph_ids\": [\"2e3339c9-e627-4a0a-8b9c-c309e219984c\", \"496d1550-9b00-4928-a5a6-61715037ba9c\"]}",
        "NodeID": "port+ucsd-data-sw:TwentyFiveGigE0/0/0/18/1",
        "Class": "ConnectionPoint",
        "Labels": "{\"local_name\": \"TwentyFiveGigE0/0/0/18/1\", \"mac\": \"7c:f8:80:8e:4d:4d\"}",
        "id": "561",
        "Capacities": "{\"bw\": 25}",
        "StitchNode": "false",
        "Name": "TwentyFiveGigE0/0/0/18/1"
      },
      "elementId": "2337"
    }
  },
  {
    "cp": {
      "identity": 2317,
      "labels": [
        "ConnectionPoint",
        "GraphNode"
      ],
      "properties": {
        "LabelDelegations": "{\"2e3339c9-e627-4a0a-8b9c-c309e219984c\": {\"pool_id\": \"_\", \"labels\": {\"mac\": \"7c:f8:80:8e:4d:04\", \"local_name\": \"HundredGigE0/0/0/0\"}}}",
        "Type": "TrunkPort",
        "GraphID": "13bccb17-1824-4941-a775-9b0a6db13cab",
        "CapacityDelegations": "{\"2e3339c9-e627-4a0a-8b9c-c309e219984c\": {\"pool_id\": \"_\", \"capacities\": {\"bw\": 100}}}",
        "StructuralInfo": "{\"adm_graph_ids\": [\"2e3339c9-e627-4a0a-8b9c-c309e219984c\", \"496d1550-9b00-4928-a5a6-61715037ba9c\"]}",
        "NodeID": "port+ucsd-data-sw:HundredGigE0/0/0/0",
        "Class": "ConnectionPoint",
        "Labels": "{\"local_name\": \"HundredGigE0/0/0/0\", \"mac\": \"7c:f8:80:8e:4d:04\"}",
        "id": "541",
        "Capacities": "{\"bw\": 100}",
        "StitchNode": "false",
        "Name": "HundredGigE0/0/0/0"
      },
      "elementId": "2317"
    }
  },
  {
    "cp": {
      "identity": 2338,
      "labels": [
        "ConnectionPoint",
        "GraphNode"
      ],
      "properties": {
        "LabelDelegations": "{\"2e3339c9-e627-4a0a-8b9c-c309e219984c\": {\"pool_id\": \"_\", \"labels\": {\"mac\": \"7c:f8:80:8e:4d:4e\", \"local_name\": \"TwentyFiveGigE0/0/0/18/2\"}}}",
        "Type": "TrunkPort",
        "GraphID": "13bccb17-1824-4941-a775-9b0a6db13cab",
        "CapacityDelegations": "{\"2e3339c9-e627-4a0a-8b9c-c309e219984c\": {\"pool_id\": \"_\", \"capacities\": {\"bw\": 25}}}",
        "StructuralInfo": "{\"adm_graph_ids\": [\"2e3339c9-e627-4a0a-8b9c-c309e219984c\", \"496d1550-9b00-4928-a5a6-61715037ba9c\"]}",
        "NodeID": "port+ucsd-data-sw:TwentyFiveGigE0/0/0/18/2",
        "Class": "ConnectionPoint",
        "Labels": "{\"local_name\": \"TwentyFiveGigE0/0/0/18/2\", \"mac\": \"7c:f8:80:8e:4d:4e\"}",
        "id": "562",
        "Capacities": "{\"bw\": 25}",
        "StitchNode": "false",
        "Name": "TwentyFiveGigE0/0/0/18/2"
      },
      "elementId": "2338"
    }
  },
  {
    "cp": {
      "identity": 2321,
      "labels": [
        "ConnectionPoint",
        "GraphNode"
      ],
      "properties": {
        "LabelDelegations": "{\"2e3339c9-e627-4a0a-8b9c-c309e219984c\": {\"pool_id\": \"_\", \"labels\": {\"mac\": \"7c:f8:80:8e:4d:0c\", \"local_name\": \"HundredGigE0/0/0/2\"}}}",
        "Type": "TrunkPort",
        "GraphID": "13bccb17-1824-4941-a775-9b0a6db13cab",
        "CapacityDelegations": "{\"2e3339c9-e627-4a0a-8b9c-c309e219984c\": {\"pool_id\": \"_\", \"capacities\": {\"bw\": 100}}}",
        "StructuralInfo": "{\"adm_graph_ids\": [\"2e3339c9-e627-4a0a-8b9c-c309e219984c\", \"496d1550-9b00-4928-a5a6-61715037ba9c\"]}",
        "NodeID": "port+ucsd-data-sw:HundredGigE0/0/0/2",
        "Class": "ConnectionPoint",
        "Labels": "{\"local_name\": \"HundredGigE0/0/0/2\", \"mac\": \"7c:f8:80:8e:4d:0c\"}",
        "id": "545",
        "Capacities": "{\"bw\": 100}",
        "StitchNode": "false",
        "Name": "HundredGigE0/0/0/2"
      },
      "elementId": "2321"
    }
  },
  {
    "cp": {
      "identity": 2326,
      "labels": [
        "ConnectionPoint",
        "GraphNode"
      ],
      "properties": {
        "LabelDelegations": "{\"2e3339c9-e627-4a0a-8b9c-c309e219984c\": {\"pool_id\": \"_\", \"labels\": {\"mac\": \"7c:f8:80:8e:4d:18\", \"local_name\": \"HundredGigE0/0/0/5\"}}}",
        "Type": "TrunkPort",
        "GraphID": "13bccb17-1824-4941-a775-9b0a6db13cab",
        "CapacityDelegations": "{\"2e3339c9-e627-4a0a-8b9c-c309e219984c\": {\"pool_id\": \"_\", \"capacities\": {\"bw\": 100}}}",
        "StructuralInfo": "{\"adm_graph_ids\": [\"2e3339c9-e627-4a0a-8b9c-c309e219984c\", \"496d1550-9b00-4928-a5a6-61715037ba9c\"]}",
        "NodeID": "port+ucsd-data-sw:HundredGigE0/0/0/5",
        "Class": "ConnectionPoint",
        "Labels": "{\"local_name\": \"HundredGigE0/0/0/5\", \"mac\": \"7c:f8:80:8e:4d:18\"}",
        "id": "550",
        "Capacities": "{\"bw\": 100}",
        "StitchNode": "false",
        "Name": "HundredGigE0/0/0/5"
      },
      "elementId": "2326"
    }
  },
  {
    "cp": {
      "identity": 4372,
      "labels": [
        "ConnectionPoint",
        "GraphNode"
      ],
      "properties": {
        "LabelDelegations": "{\"2e3339c9-e627-4a0a-8b9c-c309e219984c\": {\"pool_id\": \"_\", \"labels\": {\"mac\": \"7c:f8:80:8e:4d:30\", \"local_name\": \"HundredGigE0/0/0/11\"}}}",
        "Type": "TrunkPort",
        "GraphID": "13bccb17-1824-4941-a775-9b0a6db13cab",
        "CapacityDelegations": "{\"2e3339c9-e627-4a0a-8b9c-c309e219984c\": {\"pool_id\": \"_\", \"capacities\": {\"bw\": 100}}}",
        "StructuralInfo": "{\"adm_graph_ids\": [\"2e3339c9-e627-4a0a-8b9c-c309e219984c\", \"496d1550-9b00-4928-a5a6-61715037ba9c\"]}",
        "NodeID": "port+ucsd-data-sw:HundredGigE0/0/0/11",
        "Class": "ConnectionPoint",
        "Labels": "{\"local_name\": \"HundredGigE0/0/0/11\", \"mac\": \"7c:f8:80:8e:4d:30\"}",
        "id": "543",
        "Capacities": "{\"bw\": 100}",
        "StitchNode": "false",
        "Name": "HundredGigE0/0/0/11"
      },
      "elementId": "4372"
    }
  },
  {
    "cp": {
      "identity": 4389,
      "labels": [
        "ConnectionPoint",
        "GraphNode"
      ],
      "properties": {
        "LabelDelegations": "{\"2e3339c9-e627-4a0a-8b9c-c309e219984c\": {\"pool_id\": \"_\", \"labels\": {\"mac\": \"7c:f8:80:8e:4d:4c\", \"local_name\": \"TwentyFiveGigE0/0/0/18/0\"}}}",
        "Type": "TrunkPort",
        "GraphID": "13bccb17-1824-4941-a775-9b0a6db13cab",
        "CapacityDelegations": "{\"2e3339c9-e627-4a0a-8b9c-c309e219984c\": {\"pool_id\": \"_\", \"capacities\": {\"bw\": 25}}}",
        "StructuralInfo": "{\"adm_graph_ids\": [\"2e3339c9-e627-4a0a-8b9c-c309e219984c\", \"496d1550-9b00-4928-a5a6-61715037ba9c\"]}",
        "NodeID": "port+ucsd-data-sw:TwentyFiveGigE0/0/0/18/0",
        "Class": "ConnectionPoint",
        "Labels": "{\"local_name\": \"TwentyFiveGigE0/0/0/18/0\", \"mac\": \"7c:f8:80:8e:4d:4c\"}",
        "id": "560",
        "Capacities": "{\"bw\": 25}",
        "StitchNode": "false",
        "Name": "TwentyFiveGigE0/0/0/18/0"
      },
      "elementId": "4389"
    }
  },
  {
    "cp": {
      "identity": 4370,
      "labels": [
        "ConnectionPoint",
        "GraphNode"
      ],
      "properties": {
        "LabelDelegations": "{\"2e3339c9-e627-4a0a-8b9c-c309e219984c\": {\"pool_id\": \"_\", \"labels\": {\"mac\": \"7c:f8:80:8e:4d:04\", \"local_name\": \"HundredGigE0/0/0/0\"}}}",
        "Type": "TrunkPort",
        "GraphID": "13bccb17-1824-4941-a775-9b0a6db13cab",
        "CapacityDelegations": "{\"2e3339c9-e627-4a0a-8b9c-c309e219984c\": {\"pool_id\": \"_\", \"capacities\": {\"bw\": 100}}}",
        "StructuralInfo": "{\"adm_graph_ids\": [\"2e3339c9-e627-4a0a-8b9c-c309e219984c\", \"496d1550-9b00-4928-a5a6-61715037ba9c\"]}",
        "NodeID": "port+ucsd-data-sw:HundredGigE0/0/0/0",
        "Class": "ConnectionPoint",
        "Labels": "{\"local_name\": \"HundredGigE0/0/0/0\", \"mac\": \"7c:f8:80:8e:4d:04\"}",
        "id": "541",
        "Capacities": "{\"bw\": 100}",
        "StitchNode": "false",
        "Name": "HundredGigE0/0/0/0"
      },
      "elementId": "4370"
    }
  },
  {
    "cp": {
      "identity": 4373,
      "labels": [
        "ConnectionPoint",
        "GraphNode"
      ],
      "properties": {
        "LabelDelegations": "{\"2e3339c9-e627-4a0a-8b9c-c309e219984c\": {\"pool_id\": \"_\", \"labels\": {\"mac\": \"7c:f8:80:8e:4d:38\", \"local_name\": \"HundredGigE0/0/0/13\"}}}",
        "Type": "TrunkPort",
        "GraphID": "13bccb17-1824-4941-a775-9b0a6db13cab",
        "CapacityDelegations": "{\"2e3339c9-e627-4a0a-8b9c-c309e219984c\": {\"pool_id\": \"_\", \"capacities\": {\"bw\": 100}}}",
        "StructuralInfo": "{\"adm_graph_ids\": [\"2e3339c9-e627-4a0a-8b9c-c309e219984c\", \"496d1550-9b00-4928-a5a6-61715037ba9c\"]}",
        "NodeID": "port+ucsd-data-sw:HundredGigE0/0/0/13",
        "Class": "ConnectionPoint",
        "Labels": "{\"local_name\": \"HundredGigE0/0/0/13\", \"mac\": \"7c:f8:80:8e:4d:38\"}",
        "id": "544",
        "Capacities": "{\"bw\": 100}",
        "StitchNode": "false",
        "Name": "HundredGigE0/0/0/13"
      },
      "elementId": "4373"
    }
  },
  {
    "cp": {
      "identity": 4378,
      "labels": [
        "ConnectionPoint",
        "GraphNode"
      ],
      "properties": {
        "LabelDelegations": "{\"2e3339c9-e627-4a0a-8b9c-c309e219984c\": {\"pool_id\": \"_\", \"labels\": {\"mac\": \"7c:f8:80:8e:4d:14\", \"local_name\": \"HundredGigE0/0/0/4\"}}}",
        "Type": "TrunkPort",
        "GraphID": "13bccb17-1824-4941-a775-9b0a6db13cab",
        "CapacityDelegations": "{\"2e3339c9-e627-4a0a-8b9c-c309e219984c\": {\"pool_id\": \"_\", \"capacities\": {\"bw\": 100}}}",
        "StructuralInfo": "{\"adm_graph_ids\": [\"2e3339c9-e627-4a0a-8b9c-c309e219984c\", \"496d1550-9b00-4928-a5a6-61715037ba9c\"]}",
        "NodeID": "port+ucsd-data-sw:HundredGigE0/0/0/4",
        "Class": "ConnectionPoint",
        "Labels": "{\"local_name\": \"HundredGigE0/0/0/4\", \"mac\": \"7c:f8:80:8e:4d:14\"}",
        "id": "549",
        "Capacities": "{\"bw\": 100}",
        "StitchNode": "false",
        "Name": "HundredGigE0/0/0/4"
      },
      "elementId": "4378"
    }
  },
  {
    "cp": {
      "identity": 4376,
      "labels": [
        "ConnectionPoint",
        "GraphNode"
      ],
      "properties": {
        "LabelDelegations": "{\"2e3339c9-e627-4a0a-8b9c-c309e219984c\": {\"pool_id\": \"_\", \"labels\": {\"mac\": \"7c:f8:80:8e:4d:5c\", \"ipv4\": \"10.132.0.154\", \"ipv6\": \"2602:fcfb:8:1024::1a\", \"local_name\": \"HundredGigE0/0/0/22.3100\"}}}",
        "Type": "TrunkPort",
        "GraphID": "13bccb17-1824-4941-a775-9b0a6db13cab",
        "CapacityDelegations": "{\"2e3339c9-e627-4a0a-8b9c-c309e219984c\": {\"pool_id\": \"_\", \"capacities\": {\"bw\": 100}}}",
        "StructuralInfo": "{\"adm_graph_ids\": [\"2e3339c9-e627-4a0a-8b9c-c309e219984c\"]}",
        "NodeID": "port+ucsd-data-sw:HundredGigE0/0/0/22.3100",
        "Class": "ConnectionPoint",
        "Labels": "{\"ipv4\": \"10.132.0.154\", \"ipv6\": \"2602:fcfb:8:1024::1a\", \"local_name\": \"HundredGigE0/0/0/22.3100\", \"mac\": \"7c:f8:80:8e:4d:5c\"}",
        "id": "547",
        "Capacities": "{\"bw\": 100}",
        "StitchNode": "false",
        "Name": "HundredGigE0/0/0/22.3100"
      },
      "elementId": "4376"
    }
  },
  {
    "cp": {
      "identity": 4385,
      "labels": [
        "ConnectionPoint",
        "GraphNode"
      ],
      "properties": {
        "LabelDelegations": "{\"2e3339c9-e627-4a0a-8b9c-c309e219984c\": {\"pool_id\": \"_\", \"labels\": {\"mac\": \"7c:f8:80:8e:4d:44\", \"local_name\": \"TwentyFiveGigE0/0/0/16/0\"}}}",
        "Type": "TrunkPort",
        "GraphID": "13bccb17-1824-4941-a775-9b0a6db13cab",
        "CapacityDelegations": "{\"2e3339c9-e627-4a0a-8b9c-c309e219984c\": {\"pool_id\": \"_\", \"capacities\": {\"bw\": 25}}}",
        "StructuralInfo": "{\"adm_graph_ids\": [\"2e3339c9-e627-4a0a-8b9c-c309e219984c\", \"496d1550-9b00-4928-a5a6-61715037ba9c\"]}",
        "NodeID": "port+ucsd-data-sw:TwentyFiveGigE0/0/0/16/0",
        "Class": "ConnectionPoint",
        "Labels": "{\"local_name\": \"TwentyFiveGigE0/0/0/16/0\", \"mac\": \"7c:f8:80:8e:4d:44\"}",
        "id": "556",
        "Capacities": "{\"bw\": 25}",
        "StitchNode": "false",
        "Name": "TwentyFiveGigE0/0/0/16/0"
      },
      "elementId": "4385"
    }
  },
  {
    "cp": {
      "identity": 4379,
      "labels": [
        "ConnectionPoint",
        "GraphNode"
      ],
      "properties": {
        "LabelDelegations": "{\"2e3339c9-e627-4a0a-8b9c-c309e219984c\": {\"pool_id\": \"_\", \"labels\": {\"mac\": \"7c:f8:80:8e:4d:18\", \"local_name\": \"HundredGigE0/0/0/5\"}}}",
        "Type": "TrunkPort",
        "GraphID": "13bccb17-1824-4941-a775-9b0a6db13cab",
        "CapacityDelegations": "{\"2e3339c9-e627-4a0a-8b9c-c309e219984c\": {\"pool_id\": \"_\", \"capacities\": {\"bw\": 100}}}",
        "StructuralInfo": "{\"adm_graph_ids\": [\"2e3339c9-e627-4a0a-8b9c-c309e219984c\", \"496d1550-9b00-4928-a5a6-61715037ba9c\"]}",
        "NodeID": "port+ucsd-data-sw:HundredGigE0/0/0/5",
        "Class": "ConnectionPoint",
        "Labels": "{\"local_name\": \"HundredGigE0/0/0/5\", \"mac\": \"7c:f8:80:8e:4d:18\"}",
        "id": "550",
        "Capacities": "{\"bw\": 100}",
        "StitchNode": "false",
        "Name": "HundredGigE0/0/0/5"
      },
      "elementId": "4379"
    }
  },
  {
    "cp": {
      "identity": 4374,
      "labels": [
        "ConnectionPoint",
        "GraphNode"
      ],
      "properties": {
        "LabelDelegations": "{\"2e3339c9-e627-4a0a-8b9c-c309e219984c\": {\"pool_id\": \"_\", \"labels\": {\"mac\": \"7c:f8:80:8e:4d:0c\", \"local_name\": \"HundredGigE0/0/0/2\"}}}",
        "Type": "TrunkPort",
        "GraphID": "13bccb17-1824-4941-a775-9b0a6db13cab",
        "CapacityDelegations": "{\"2e3339c9-e627-4a0a-8b9c-c309e219984c\": {\"pool_id\": \"_\", \"capacities\": {\"bw\": 100}}}",
        "StructuralInfo": "{\"adm_graph_ids\": [\"2e3339c9-e627-4a0a-8b9c-c309e219984c\", \"496d1550-9b00-4928-a5a6-61715037ba9c\"]}",
        "NodeID": "port+ucsd-data-sw:HundredGigE0/0/0/2",
        "Class": "ConnectionPoint",
        "Labels": "{\"local_name\": \"HundredGigE0/0/0/2\", \"mac\": \"7c:f8:80:8e:4d:0c\"}",
        "id": "545",
        "Capacities": "{\"bw\": 100}",
        "StitchNode": "false",
        "Name": "HundredGigE0/0/0/2"
      },
      "elementId": "4374"
    }
  },
  {
    "cp": {
      "identity": 4391,
      "labels": [
        "ConnectionPoint",
        "GraphNode"
      ],
      "properties": {
        "LabelDelegations": "{\"2e3339c9-e627-4a0a-8b9c-c309e219984c\": {\"pool_id\": \"_\", \"labels\": {\"mac\": \"7c:f8:80:8e:4d:4e\", \"local_name\": \"TwentyFiveGigE0/0/0/18/2\"}}}",
        "Type": "TrunkPort",
        "GraphID": "13bccb17-1824-4941-a775-9b0a6db13cab",
        "CapacityDelegations": "{\"2e3339c9-e627-4a0a-8b9c-c309e219984c\": {\"pool_id\": \"_\", \"capacities\": {\"bw\": 25}}}",
        "StructuralInfo": "{\"adm_graph_ids\": [\"2e3339c9-e627-4a0a-8b9c-c309e219984c\", \"496d1550-9b00-4928-a5a6-61715037ba9c\"]}",
        "NodeID": "port+ucsd-data-sw:TwentyFiveGigE0/0/0/18/2",
        "Class": "ConnectionPoint",
        "Labels": "{\"local_name\": \"TwentyFiveGigE0/0/0/18/2\", \"mac\": \"7c:f8:80:8e:4d:4e\"}",
        "id": "562",
        "Capacities": "{\"bw\": 25}",
        "StitchNode": "false",
        "Name": "TwentyFiveGigE0/0/0/18/2"
      },
      "elementId": "4391"
    }
  },
  {
    "cp": {
      "identity": 4390,
      "labels": [
        "ConnectionPoint",
        "GraphNode"
      ],
      "properties": {
        "LabelDelegations": "{\"2e3339c9-e627-4a0a-8b9c-c309e219984c\": {\"pool_id\": \"_\", \"labels\": {\"mac\": \"7c:f8:80:8e:4d:4d\", \"local_name\": \"TwentyFiveGigE0/0/0/18/1\"}}}",
        "Type": "TrunkPort",
        "GraphID": "13bccb17-1824-4941-a775-9b0a6db13cab",
        "CapacityDelegations": "{\"2e3339c9-e627-4a0a-8b9c-c309e219984c\": {\"pool_id\": \"_\", \"capacities\": {\"bw\": 25}}}",
        "StructuralInfo": "{\"adm_graph_ids\": [\"2e3339c9-e627-4a0a-8b9c-c309e219984c\", \"496d1550-9b00-4928-a5a6-61715037ba9c\"]}",
        "NodeID": "port+ucsd-data-sw:TwentyFiveGigE0/0/0/18/1",
        "Class": "ConnectionPoint",
        "Labels": "{\"local_name\": \"TwentyFiveGigE0/0/0/18/1\", \"mac\": \"7c:f8:80:8e:4d:4d\"}",
        "id": "561",
        "Capacities": "{\"bw\": 25}",
        "StitchNode": "false",
        "Name": "TwentyFiveGigE0/0/0/18/1"
      },
      "elementId": "4390"
    }
  },
  {
    "cp": {
      "identity": 4388,
      "labels": [
        "ConnectionPoint",
        "GraphNode"
      ],
      "properties": {
        "LabelDelegations": "{\"2e3339c9-e627-4a0a-8b9c-c309e219984c\": {\"pool_id\": \"_\", \"labels\": {\"mac\": \"7c:f8:80:8e:4d:47\", \"local_name\": \"TwentyFiveGigE0/0/0/16/3\"}}}",
        "Type": "TrunkPort",
        "GraphID": "13bccb17-1824-4941-a775-9b0a6db13cab",
        "CapacityDelegations": "{\"2e3339c9-e627-4a0a-8b9c-c309e219984c\": {\"pool_id\": \"_\", \"capacities\": {\"bw\": 25}}}",
        "StructuralInfo": "{\"adm_graph_ids\": [\"2e3339c9-e627-4a0a-8b9c-c309e219984c\", \"496d1550-9b00-4928-a5a6-61715037ba9c\"]}",
        "NodeID": "port+ucsd-data-sw:TwentyFiveGigE0/0/0/16/3",
        "Class": "ConnectionPoint",
        "Labels": "{\"local_name\": \"TwentyFiveGigE0/0/0/16/3\", \"mac\": \"7c:f8:80:8e:4d:47\"}",
        "id": "559",
        "Capacities": "{\"bw\": 25}",
        "StitchNode": "false",
        "Name": "TwentyFiveGigE0/0/0/16/3"
      },
      "elementId": "4388"
    }
  },
  {
    "cp": {
      "identity": 4387,
      "labels": [
        "ConnectionPoint",
        "GraphNode"
      ],
      "properties": {
        "LabelDelegations": "{\"2e3339c9-e627-4a0a-8b9c-c309e219984c\": {\"pool_id\": \"_\", \"labels\": {\"mac\": \"7c:f8:80:8e:4d:46\", \"local_name\": \"TwentyFiveGigE0/0/0/16/2\"}}}",
        "Type": "TrunkPort",
        "GraphID": "13bccb17-1824-4941-a775-9b0a6db13cab",
        "CapacityDelegations": "{\"2e3339c9-e627-4a0a-8b9c-c309e219984c\": {\"pool_id\": \"_\", \"capacities\": {\"bw\": 25}}}",
        "StructuralInfo": "{\"adm_graph_ids\": [\"2e3339c9-e627-4a0a-8b9c-c309e219984c\", \"496d1550-9b00-4928-a5a6-61715037ba9c\"]}",
        "NodeID": "port+ucsd-data-sw:TwentyFiveGigE0/0/0/16/2",
        "Class": "ConnectionPoint",
        "Labels": "{\"local_name\": \"TwentyFiveGigE0/0/0/16/2\", \"mac\": \"7c:f8:80:8e:4d:46\"}",
        "id": "558",
        "Capacities": "{\"bw\": 25}",
        "StitchNode": "false",
        "Name": "TwentyFiveGigE0/0/0/16/2"
      },
      "elementId": "4387"
    }
  },
  {
    "cp": {
      "identity": 4383,
      "labels": [
        "ConnectionPoint",
        "GraphNode"
      ],
      "properties": {
        "LabelDelegations": "{\"2e3339c9-e627-4a0a-8b9c-c309e219984c\": {\"pool_id\": \"_\", \"labels\": {\"mac\": \"7c:f8:80:8e:4d:20\", \"local_name\": \"HundredGigE0/0/0/7\"}}}",
        "Type": "TrunkPort",
        "GraphID": "13bccb17-1824-4941-a775-9b0a6db13cab",
        "CapacityDelegations": "{\"2e3339c9-e627-4a0a-8b9c-c309e219984c\": {\"pool_id\": \"_\", \"capacities\": {\"bw\": 100}}}",
        "StructuralInfo": "{\"adm_graph_ids\": [\"2e3339c9-e627-4a0a-8b9c-c309e219984c\", \"496d1550-9b00-4928-a5a6-61715037ba9c\"]}",
        "NodeID": "port+ucsd-data-sw:HundredGigE0/0/0/7",
        "Class": "ConnectionPoint",
        "Labels": "{\"local_name\": \"HundredGigE0/0/0/7\", \"mac\": \"7c:f8:80:8e:4d:20\"}",
        "id": "554",
        "Capacities": "{\"bw\": 100}",
        "StitchNode": "false",
        "Name": "HundredGigE0/0/0/7"
      },
      "elementId": "4383"
    }
  },
  {
    "cp": {
      "identity": 4392,
      "labels": [
        "ConnectionPoint",
        "GraphNode"
      ],
      "properties": {
        "LabelDelegations": "{\"2e3339c9-e627-4a0a-8b9c-c309e219984c\": {\"pool_id\": \"_\", \"labels\": {\"mac\": \"7c:f8:80:8e:4d:4f\", \"local_name\": \"TwentyFiveGigE0/0/0/18/3\"}}}",
        "Type": "TrunkPort",
        "GraphID": "13bccb17-1824-4941-a775-9b0a6db13cab",
        "CapacityDelegations": "{\"2e3339c9-e627-4a0a-8b9c-c309e219984c\": {\"pool_id\": \"_\", \"capacities\": {\"bw\": 25}}}",
        "StructuralInfo": "{\"adm_graph_ids\": [\"2e3339c9-e627-4a0a-8b9c-c309e219984c\", \"496d1550-9b00-4928-a5a6-61715037ba9c\"]}",
        "NodeID": "port+ucsd-data-sw:TwentyFiveGigE0/0/0/18/3",
        "Class": "ConnectionPoint",
        "Labels": "{\"local_name\": \"TwentyFiveGigE0/0/0/18/3\", \"mac\": \"7c:f8:80:8e:4d:4f\"}",
        "id": "563",
        "Capacities": "{\"bw\": 25}",
        "StitchNode": "false",
        "Name": "TwentyFiveGigE0/0/0/18/3"
      },
      "elementId": "4392"
    }
  },
  {
    "cp": {
      "identity": 4386,
      "labels": [
        "ConnectionPoint",
        "GraphNode"
      ],
      "properties": {
        "LabelDelegations": "{\"2e3339c9-e627-4a0a-8b9c-c309e219984c\": {\"pool_id\": \"_\", \"labels\": {\"mac\": \"7c:f8:80:8e:4d:45\", \"local_name\": \"TwentyFiveGigE0/0/0/16/1\"}}}",
        "Type": "TrunkPort",
        "GraphID": "13bccb17-1824-4941-a775-9b0a6db13cab",
        "CapacityDelegations": "{\"2e3339c9-e627-4a0a-8b9c-c309e219984c\": {\"pool_id\": \"_\", \"capacities\": {\"bw\": 25}}}",
        "StructuralInfo": "{\"adm_graph_ids\": [\"2e3339c9-e627-4a0a-8b9c-c309e219984c\", \"496d1550-9b00-4928-a5a6-61715037ba9c\"]}",
        "NodeID": "port+ucsd-data-sw:TwentyFiveGigE0/0/0/16/1",
        "Class": "ConnectionPoint",
        "Labels": "{\"local_name\": \"TwentyFiveGigE0/0/0/16/1\", \"mac\": \"7c:f8:80:8e:4d:45\"}",
        "id": "557",
        "Capacities": "{\"bw\": 25}",
        "StitchNode": "false",
        "Name": "TwentyFiveGigE0/0/0/16/1"
      },
      "elementId": "4386"
    }
  },
  {
    "cp": {
      "identity": 4382,
      "labels": [
        "ConnectionPoint",
        "GraphNode"
      ],
      "properties": {
        "LabelDelegations": "{\"2e3339c9-e627-4a0a-8b9c-c309e219984c\": {\"pool_id\": \"_\", \"labels\": {\"mac\": \"7c:f8:80:8e:4d:1c\", \"local_name\": \"HundredGigE0/0/0/6\"}}}",
        "Type": "TrunkPort",
        "GraphID": "13bccb17-1824-4941-a775-9b0a6db13cab",
        "CapacityDelegations": "{\"2e3339c9-e627-4a0a-8b9c-c309e219984c\": {\"pool_id\": \"_\", \"capacities\": {\"bw\": 100}}}",
        "StructuralInfo": "{\"adm_graph_ids\": [\"2e3339c9-e627-4a0a-8b9c-c309e219984c\", \"496d1550-9b00-4928-a5a6-61715037ba9c\"]}",
        "NodeID": "port+ucsd-data-sw:HundredGigE0/0/0/6",
        "Class": "ConnectionPoint",
        "Labels": "{\"local_name\": \"HundredGigE0/0/0/6\", \"mac\": \"7c:f8:80:8e:4d:1c\"}",
        "id": "553",
        "Capacities": "{\"bw\": 100}",
        "StitchNode": "false",
        "Name": "HundredGigE0/0/0/6"
      },
      "elementId": "4382"
    }
  },
  {
    "cp": {
      "identity": 4384,
      "labels": [
        "ConnectionPoint",
        "GraphNode"
      ],
      "properties": {
        "LabelDelegations": "{\"2e3339c9-e627-4a0a-8b9c-c309e219984c\": {\"pool_id\": \"_\", \"labels\": {\"mac\": \"7c:f8:80:8e:4d:28\", \"local_name\": \"HundredGigE0/0/0/9\"}}}",
        "Type": "TrunkPort",
        "GraphID": "13bccb17-1824-4941-a775-9b0a6db13cab",
        "CapacityDelegations": "{\"2e3339c9-e627-4a0a-8b9c-c309e219984c\": {\"pool_id\": \"_\", \"capacities\": {\"bw\": 100}}}",
        "StructuralInfo": "{\"adm_graph_ids\": [\"2e3339c9-e627-4a0a-8b9c-c309e219984c\", \"496d1550-9b00-4928-a5a6-61715037ba9c\"]}",
        "NodeID": "port+ucsd-data-sw:HundredGigE0/0/0/9",
        "Class": "ConnectionPoint",
        "Labels": "{\"local_name\": \"HundredGigE0/0/0/9\", \"mac\": \"7c:f8:80:8e:4d:28\"}",
        "id": "555",
        "Capacities": "{\"bw\": 100}",
        "StitchNode": "false",
        "Name": "HundredGigE0/0/0/9"
      },
      "elementId": "4384"
    }
  },
  {
    "cp": {
      "identity": 8736,
      "labels": [
        "ConnectionPoint",
        "GraphNode"
      ],
      "properties": {
        "LabelDelegations": "{\"609048fb-8416-463d-9f79-c3671cec197e\": {\"pool_id\": \"_\", \"labels\": {\"mac\": \"7c:f8:80:8e:4d:47\", \"local_name\": \"TwentyFiveGigE0/0/0/16/3\"}}}",
        "Type": "TrunkPort",
        "GraphID": "40df44eb-1e69-409b-9f46-c3a975338659",
        "CapacityDelegations": "{\"609048fb-8416-463d-9f79-c3671cec197e\": {\"pool_id\": \"_\", \"capacities\": {\"bw\": 25}}}",
        "StructuralInfo": "{\"adm_graph_ids\": [\"609048fb-8416-463d-9f79-c3671cec197e\", \"992f4a14-8005-445f-ad9a-07db92cc5366\"]}",
        "NodeID": "port+ucsd-data-sw:TwentyFiveGigE0/0/0/16/3",
        "Class": "ConnectionPoint",
        "Labels": "{\"local_name\": \"TwentyFiveGigE0/0/0/16/3\", \"mac\": \"7c:f8:80:8e:4d:47\"}",
        "id": "1005",
        "Capacities": "{\"bw\": 25}",
        "StitchNode": "false",
        "Name": "TwentyFiveGigE0/0/0/16/3"
      },
      "elementId": "8736"
    }
  },
  {
    "cp": {
      "identity": 9286,
      "labels": [
        "ConnectionPoint",
        "GraphNode"
      ],
      "properties": {
        "Type": "TrunkPort",
        "GraphID": "40df44eb-1e69-409b-9f46-c3a975338659",
        "StructuralInfo": "{\"adm_graph_ids\": [\"992f4a14-8005-445f-ad9a-07db92cc5366\"]}",
        "NodeID": "port+ucsd-data-sw:HundredGigE0/0/0/25/1",
        "Class": "ConnectionPoint",
        "id": "137",
        "StitchNode": "false",
        "Name": "HundredGigE0/0/0/25/1"
      },
      "elementId": "9286"
    }
  },
  {
    "cp": {
      "identity": 8625,
      "labels": [
        "ConnectionPoint",
        "GraphNode"
      ],
      "properties": {
        "LabelDelegations": "{\"609048fb-8416-463d-9f79-c3671cec197e\": {\"pool_id\": \"_\", \"labels\": {\"mac\": \"7c:f8:80:8e:4d:58\", \"ipv4\": \"10.134.128.133\", \"ipv6\": \"2602:fcfb:d:1024::5\", \"local_name\": \"HundredGigE0/0/0/21.3000\"}}}",
        "Type": "TrunkPort",
        "GraphID": "40df44eb-1e69-409b-9f46-c3a975338659",
        "CapacityDelegations": "{\"609048fb-8416-463d-9f79-c3671cec197e\": {\"pool_id\": \"_\", \"capacities\": {\"bw\": 100}}}",
        "StructuralInfo": "{\"adm_graph_ids\": [\"609048fb-8416-463d-9f79-c3671cec197e\"]}",
        "NodeID": "port+ucsd-data-sw:HundredGigE0/0/0/21.3000",
        "Class": "ConnectionPoint",
        "Labels": "{\"ipv4\": \"10.134.128.133\", \"ipv6\": \"2602:fcfb:d:1024::5\", \"local_name\": \"HundredGigE0/0/0/21.3000\", \"mac\": \"7c:f8:80:8e:4d:58\"}",
        "id": "995",
        "Capacities": "{\"bw\": 100}",
        "StitchNode": "false",
        "Name": "HundredGigE0/0/0/21.3000"
      },
      "elementId": "8625"
    }
  },
  {
    "cp": {
      "identity": 8620,
      "labels": [
        "ConnectionPoint",
        "GraphNode"
      ],
      "properties": {
        "LabelDelegations": "{\"609048fb-8416-463d-9f79-c3671cec197e\": {\"pool_id\": \"_\", \"labels\": {\"mac\": \"7c:f8:80:8e:4d:0c\", \"local_name\": \"HundredGigE0/0/0/2\"}}}",
        "Type": "TrunkPort",
        "GraphID": "40df44eb-1e69-409b-9f46-c3a975338659",
        "CapacityDelegations": "{\"609048fb-8416-463d-9f79-c3671cec197e\": {\"pool_id\": \"_\", \"capacities\": {\"bw\": 100}}}",
        "StructuralInfo": "{\"adm_graph_ids\": [\"609048fb-8416-463d-9f79-c3671cec197e\", \"992f4a14-8005-445f-ad9a-07db92cc5366\"]}",
        "NodeID": "port+ucsd-data-sw:HundredGigE0/0/0/2",
        "Class": "ConnectionPoint",
        "Labels": "{\"local_name\": \"HundredGigE0/0/0/2\", \"mac\": \"7c:f8:80:8e:4d:0c\"}",
        "id": "993",
        "Capacities": "{\"bw\": 100}",
        "StitchNode": "false",
        "Name": "HundredGigE0/0/0/2"
      },
      "elementId": "8620"
    }
  },
  {
    "cp": {
      "identity": 8636,
      "labels": [
        "ConnectionPoint",
        "GraphNode"
      ],
      "properties": {
        "LabelDelegations": "{\"609048fb-8416-463d-9f79-c3671cec197e\": {\"pool_id\": \"_\", \"labels\": {\"mac\": \"7c:f8:80:8e:4d:24\", \"local_name\": \"HundredGigE0/0/0/8\"}}}",
        "Type": "TrunkPort",
        "GraphID": "40df44eb-1e69-409b-9f46-c3a975338659",
        "CapacityDelegations": "{\"609048fb-8416-463d-9f79-c3671cec197e\": {\"pool_id\": \"_\", \"capacities\": {\"bw\": 100}}}",
        "StructuralInfo": "{\"adm_graph_ids\": [\"609048fb-8416-463d-9f79-c3671cec197e\", \"992f4a14-8005-445f-ad9a-07db92cc5366\"]}",
        "NodeID": "port+ucsd-data-sw:HundredGigE0/0/0/8",
        "Class": "ConnectionPoint",
        "Labels": "{\"local_name\": \"HundredGigE0/0/0/8\", \"mac\": \"7c:f8:80:8e:4d:24\"}",
        "id": "1000",
        "Capacities": "{\"bw\": 100}",
        "StitchNode": "false",
        "Name": "HundredGigE0/0/0/8"
      },
      "elementId": "8636"
    }
  },
  {
    "cp": {
      "identity": 8733,
      "labels": [
        "ConnectionPoint",
        "GraphNode"
      ],
      "properties": {
        "LabelDelegations": "{\"609048fb-8416-463d-9f79-c3671cec197e\": {\"pool_id\": \"_\", \"labels\": {\"mac\": \"7c:f8:80:8e:4d:44\", \"local_name\": \"TwentyFiveGigE0/0/0/16/0\"}}}",
        "Type": "TrunkPort",
        "GraphID": "40df44eb-1e69-409b-9f46-c3a975338659",
        "CapacityDelegations": "{\"609048fb-8416-463d-9f79-c3671cec197e\": {\"pool_id\": \"_\", \"capacities\": {\"bw\": 25}}}",
        "StructuralInfo": "{\"adm_graph_ids\": [\"609048fb-8416-463d-9f79-c3671cec197e\", \"992f4a14-8005-445f-ad9a-07db92cc5366\"]}",
        "NodeID": "port+ucsd-data-sw:TwentyFiveGigE0/0/0/16/0",
        "Class": "ConnectionPoint",
        "Labels": "{\"local_name\": \"TwentyFiveGigE0/0/0/16/0\", \"mac\": \"7c:f8:80:8e:4d:44\"}",
        "id": "1002",
        "Capacities": "{\"bw\": 25}",
        "StitchNode": "false",
        "Name": "TwentyFiveGigE0/0/0/16/0"
      },
      "elementId": "8733"
    }
  },
  {
    "cp": {
      "identity": 9274,
      "labels": [
        "ConnectionPoint",
        "GraphNode"
      ],
      "properties": {
        "Type": "TrunkPort",
        "GraphID": "40df44eb-1e69-409b-9f46-c3a975338659",
        "StructuralInfo": "{\"adm_graph_ids\": [\"992f4a14-8005-445f-ad9a-07db92cc5366\"]}",
        "NodeID": "port+ucsd-data-sw:HundredGigE0/0/0/24/0",
        "Class": "ConnectionPoint",
        "id": "127",
        "StitchNode": "false",
        "Name": "HundredGigE0/0/0/24/0"
      },
      "elementId": "9274"
    }
  },
  {
    "cp": {
      "identity": 9289,
      "labels": [
        "ConnectionPoint",
        "GraphNode"
      ],
      "properties": {
        "Type": "TrunkPort",
        "GraphID": "40df44eb-1e69-409b-9f46-c3a975338659",
        "StructuralInfo": "{\"adm_graph_ids\": [\"992f4a14-8005-445f-ad9a-07db92cc5366\"]}",
        "NodeID": "port+ucsd-data-sw:HundredGigE0/0/0/25/2",
        "Class": "ConnectionPoint",
        "id": "139",
        "StitchNode": "false",
        "Name": "HundredGigE0/0/0/25/2"
      },
      "elementId": "9289"
    }
  },
  {
    "cp": {
      "identity": 8618,
      "labels": [
        "ConnectionPoint",
        "GraphNode"
      ],
      "properties": {
        "LabelDelegations": "{\"609048fb-8416-463d-9f79-c3671cec197e\": {\"pool_id\": \"_\", \"labels\": {\"mac\": \"7c:f8:80:8e:4d:38\", \"local_name\": \"HundredGigE0/0/0/13\"}}}",
        "Type": "TrunkPort",
        "GraphID": "40df44eb-1e69-409b-9f46-c3a975338659",
        "CapacityDelegations": "{\"609048fb-8416-463d-9f79-c3671cec197e\": {\"pool_id\": \"_\", \"capacities\": {\"bw\": 100}}}",
        "StructuralInfo": "{\"adm_graph_ids\": [\"609048fb-8416-463d-9f79-c3671cec197e\", \"992f4a14-8005-445f-ad9a-07db92cc5366\"]}",
        "NodeID": "port+ucsd-data-sw:HundredGigE0/0/0/13",
        "Class": "ConnectionPoint",
        "Labels": "{\"local_name\": \"HundredGigE0/0/0/13\", \"mac\": \"7c:f8:80:8e:4d:38\"}",
        "id": "992",
        "Capacities": "{\"bw\": 100}",
        "StitchNode": "false",
        "Name": "HundredGigE0/0/0/13"
      },
      "elementId": "8618"
    }
  },
  {
    "cp": {
      "identity": 8616,
      "labels": [
        "ConnectionPoint",
        "GraphNode"
      ],
      "properties": {
        "LabelDelegations": "{\"609048fb-8416-463d-9f79-c3671cec197e\": {\"pool_id\": \"_\", \"labels\": {\"mac\": \"7c:f8:80:8e:4d:30\", \"local_name\": \"HundredGigE0/0/0/11\"}}}",
        "Type": "TrunkPort",
        "GraphID": "40df44eb-1e69-409b-9f46-c3a975338659",
        "CapacityDelegations": "{\"609048fb-8416-463d-9f79-c3671cec197e\": {\"pool_id\": \"_\", \"capacities\": {\"bw\": 100}}}",
        "StructuralInfo": "{\"adm_graph_ids\": [\"609048fb-8416-463d-9f79-c3671cec197e\", \"992f4a14-8005-445f-ad9a-07db92cc5366\"]}",
        "NodeID": "port+ucsd-data-sw:HundredGigE0/0/0/11",
        "Class": "ConnectionPoint",
        "Labels": "{\"local_name\": \"HundredGigE0/0/0/11\", \"mac\": \"7c:f8:80:8e:4d:30\"}",
        "id": "991",
        "Capacities": "{\"bw\": 100}",
        "StitchNode": "false",
        "Name": "HundredGigE0/0/0/11"
      },
      "elementId": "8616"
    }
  },
  {
    "cp": {
      "identity": 9278,
      "labels": [
        "ConnectionPoint",
        "GraphNode"
      ],
      "properties": {
        "Type": "TrunkPort",
        "GraphID": "40df44eb-1e69-409b-9f46-c3a975338659",
        "StructuralInfo": "{\"adm_graph_ids\": [\"992f4a14-8005-445f-ad9a-07db92cc5366\"]}",
        "NodeID": "port+ucsd-data-sw:HundredGigE0/0/0/24/2",
        "Class": "ConnectionPoint",
        "id": "131",
        "StitchNode": "false",
        "Name": "HundredGigE0/0/0/24/2"
      },
      "elementId": "9278"
    }
  },
  {
    "cp": {
      "identity": 8734,
      "labels": [
        "ConnectionPoint",
        "GraphNode"
      ],
      "properties": {
        "LabelDelegations": "{\"609048fb-8416-463d-9f79-c3671cec197e\": {\"pool_id\": \"_\", \"labels\": {\"mac\": \"7c:f8:80:8e:4d:45\", \"local_name\": \"TwentyFiveGigE0/0/0/16/1\"}}}",
        "Type": "TrunkPort",
        "GraphID": "40df44eb-1e69-409b-9f46-c3a975338659",
        "CapacityDelegations": "{\"609048fb-8416-463d-9f79-c3671cec197e\": {\"pool_id\": \"_\", \"capacities\": {\"bw\": 25}}}",
        "StructuralInfo": "{\"adm_graph_ids\": [\"609048fb-8416-463d-9f79-c3671cec197e\", \"992f4a14-8005-445f-ad9a-07db92cc5366\"]}",
        "NodeID": "port+ucsd-data-sw:TwentyFiveGigE0/0/0/16/1",
        "Class": "ConnectionPoint",
        "Labels": "{\"local_name\": \"TwentyFiveGigE0/0/0/16/1\", \"mac\": \"7c:f8:80:8e:4d:45\"}",
        "id": "1003",
        "Capacities": "{\"bw\": 25}",
        "StitchNode": "false",
        "Name": "TwentyFiveGigE0/0/0/16/1"
      },
      "elementId": "8734"
    }
  },
  {
    "cp": {
      "identity": 8614,
      "labels": [
        "ConnectionPoint",
        "GraphNode"
      ],
      "properties": {
        "LabelDelegations": "{\"609048fb-8416-463d-9f79-c3671cec197e\": {\"pool_id\": \"_\", \"labels\": {\"mac\": \"7c:f8:80:8e:4d:2c\", \"local_name\": \"HundredGigE0/0/0/10\"}}}",
        "Type": "TrunkPort",
        "GraphID": "40df44eb-1e69-409b-9f46-c3a975338659",
        "CapacityDelegations": "{\"609048fb-8416-463d-9f79-c3671cec197e\": {\"pool_id\": \"_\", \"capacities\": {\"bw\": 100}}}",
        "StructuralInfo": "{\"adm_graph_ids\": [\"609048fb-8416-463d-9f79-c3671cec197e\", \"992f4a14-8005-445f-ad9a-07db92cc5366\"]}",
        "NodeID": "port+ucsd-data-sw:HundredGigE0/0/0/10",
        "Class": "ConnectionPoint",
        "Labels": "{\"local_name\": \"HundredGigE0/0/0/10\", \"mac\": \"7c:f8:80:8e:4d:2c\"}",
        "id": "990",
        "Capacities": "{\"bw\": 100}",
        "StitchNode": "false",
        "Name": "HundredGigE0/0/0/10"
      },
      "elementId": "8614"
    }
  },
  {
    "cp": {
      "identity": 8603,
      "labels": [
        "ConnectionPoint",
        "GraphNode"
      ],
      "properties": {
        "LabelDelegations": "{\"609048fb-8416-463d-9f79-c3671cec197e\": {\"pool_id\": \"_\", \"labels\": {\"mac\": \"7c:f8:80:8e:4d:6c\", \"ipv4\": \"10.132.0.154\", \"ipv6\": \"2602:fcfb:8:1024::1a\", \"local_name\": \"FourHundredGigE0/0/0/26.3100\"}}}",
        "Type": "TrunkPort",
        "GraphID": "40df44eb-1e69-409b-9f46-c3a975338659",
        "CapacityDelegations": "{\"609048fb-8416-463d-9f79-c3671cec197e\": {\"pool_id\": \"_\", \"capacities\": {\"bw\": 400}}}",
        "StructuralInfo": "{\"adm_graph_ids\": [\"609048fb-8416-463d-9f79-c3671cec197e\"]}",
        "NodeID": "port+ucsd-data-sw:FourHundredGigE0/0/0/26.3100",
        "Labels": "{\"ipv4\": \"10.132.0.154\", \"ipv6\": \"2602:fcfb:8:1024::1a\", \"local_name\": \"FourHundredGigE0/0/0/26.3100\", \"mac\": \"7c:f8:80:8e:4d:6c\"}",
        "Class": "ConnectionPoint",
        "id": "983",
        "Capacities": "{\"bw\": 400}",
        "StitchNode": "false",
        "Name": "FourHundredGigE0/0/0/26.3100"
      },
      "elementId": "8603"
    }
  },
  {
    "cp": {
      "identity": 9280,
      "labels": [
        "ConnectionPoint",
        "GraphNode"
      ],
      "properties": {
        "Type": "TrunkPort",
        "GraphID": "40df44eb-1e69-409b-9f46-c3a975338659",
        "StructuralInfo": "{\"adm_graph_ids\": [\"992f4a14-8005-445f-ad9a-07db92cc5366\"]}",
        "NodeID": "port+ucsd-data-sw:HundredGigE0/0/0/24/3",
        "Class": "ConnectionPoint",
        "id": "133",
        "StitchNode": "false",
        "Name": "HundredGigE0/0/0/24/3"
      },
      "elementId": "9280"
    }
  },
  {
    "cp": {
      "identity": 8732,
      "labels": [
        "ConnectionPoint",
        "GraphNode"
      ],
      "properties": {
        "LabelDelegations": "{\"609048fb-8416-463d-9f79-c3671cec197e\": {\"pool_id\": \"_\", \"labels\": {\"mac\": \"7c:f8:80:8e:4d:28\", \"local_name\": \"HundredGigE0/0/0/9\"}}}",
        "Type": "TrunkPort",
        "GraphID": "40df44eb-1e69-409b-9f46-c3a975338659",
        "CapacityDelegations": "{\"609048fb-8416-463d-9f79-c3671cec197e\": {\"pool_id\": \"_\", \"capacities\": {\"bw\": 100}}}",
        "StructuralInfo": "{\"adm_graph_ids\": [\"609048fb-8416-463d-9f79-c3671cec197e\", \"992f4a14-8005-445f-ad9a-07db92cc5366\"]}",
        "NodeID": "port+ucsd-data-sw:HundredGigE0/0/0/9",
        "Class": "ConnectionPoint",
        "Labels": "{\"local_name\": \"HundredGigE0/0/0/9\", \"mac\": \"7c:f8:80:8e:4d:28\"}",
        "id": "1001",
        "Capacities": "{\"bw\": 100}",
        "StitchNode": "false",
        "Name": "HundredGigE0/0/0/9"
      },
      "elementId": "8732"
    }
  },
  {
    "cp": {
      "identity": 9276,
      "labels": [
        "ConnectionPoint",
        "GraphNode"
      ],
      "properties": {
        "Type": "TrunkPort",
        "GraphID": "40df44eb-1e69-409b-9f46-c3a975338659",
        "StructuralInfo": "{\"adm_graph_ids\": [\"992f4a14-8005-445f-ad9a-07db92cc5366\"]}",
        "NodeID": "port+ucsd-data-sw:HundredGigE0/0/0/24/1",
        "Class": "ConnectionPoint",
        "id": "129",
        "StitchNode": "false",
        "Name": "HundredGigE0/0/0/24/1"
      },
      "elementId": "9276"
    }
  },
  {
    "cp": {
      "identity": 8965,
      "labels": [
        "ConnectionPoint",
        "GraphNode"
      ],
      "properties": {
        "LabelDelegations": "{\"609048fb-8416-463d-9f79-c3671cec197e\": {\"pool_id\": \"_\", \"labels\": {\"mac\": \"7c:f8:80:8e:4d:6c\", \"local_name\": \"FourHundredGigE0/0/0/26\"}}}",
        "Type": "TrunkPort",
        "GraphID": "40df44eb-1e69-409b-9f46-c3a975338659",
        "CapacityDelegations": "{\"609048fb-8416-463d-9f79-c3671cec197e\": {\"pool_id\": \"_\", \"capacities\": {\"bw\": 400}}}",
        "StructuralInfo": "{\"adm_graph_ids\": [\"609048fb-8416-463d-9f79-c3671cec197e\"]}",
        "NodeID": "port+ucsd-data-sw:FourHundredGigE0/0/0/26",
        "Class": "ConnectionPoint",
        "Labels": "{\"local_name\": \"FourHundredGigE0/0/0/26\", \"mac\": \"7c:f8:80:8e:4d:6c\"}",
        "id": "978",
        "Capacities": "{\"bw\": 400}",
        "StitchNode": "false",
        "Name": "FourHundredGigE0/0/0/26"
      },
      "elementId": "8965"
    }
  },
  {
    "cp": {
      "identity": 8604,
      "labels": [
        "ConnectionPoint",
        "GraphNode"
      ],
      "properties": {
        "LabelDelegations": "{\"609048fb-8416-463d-9f79-c3671cec197e\": {\"pool_id\": \"_\", \"labels\": {\"mac\": \"7c:f8:80:8e:4d:70\", \"local_name\": \"FourHundredGigE0/0/0/27\"}}}",
        "Type": "TrunkPort",
        "GraphID": "40df44eb-1e69-409b-9f46-c3a975338659",
        "CapacityDelegations": "{\"609048fb-8416-463d-9f79-c3671cec197e\": {\"pool_id\": \"_\", \"capacities\": {\"bw\": 400}}}",
        "StructuralInfo": "{\"adm_graph_ids\": [\"609048fb-8416-463d-9f79-c3671cec197e\"]}",
        "NodeID": "port+ucsd-data-sw:FourHundredGigE0/0/0/27",
        "Class": "ConnectionPoint",
        "Labels": "{\"local_name\": \"FourHundredGigE0/0/0/27\", \"mac\": \"7c:f8:80:8e:4d:70\"}",
        "id": "984",
        "Capacities": "{\"bw\": 400}",
        "StitchNode": "false",
        "Name": "FourHundredGigE0/0/0/27"
      },
      "elementId": "8604"
    }
  },
  {
    "cp": {
      "identity": 8738,
      "labels": [
        "ConnectionPoint",
        "GraphNode"
      ],
      "properties": {
        "LabelDelegations": "{\"609048fb-8416-463d-9f79-c3671cec197e\": {\"pool_id\": \"_\", \"labels\": {\"mac\": \"7c:f8:80:8e:4d:4c\", \"local_name\": \"TwentyFiveGigE0/0/0/18/0\"}}}",
        "Type": "TrunkPort",
        "GraphID": "40df44eb-1e69-409b-9f46-c3a975338659",
        "CapacityDelegations": "{\"609048fb-8416-463d-9f79-c3671cec197e\": {\"pool_id\": \"_\", \"capacities\": {\"bw\": 25}}}",
        "StructuralInfo": "{\"adm_graph_ids\": [\"609048fb-8416-463d-9f79-c3671cec197e\", \"992f4a14-8005-445f-ad9a-07db92cc5366\"]}",
        "NodeID": "port+ucsd-data-sw:TwentyFiveGigE0/0/0/18/0",
        "Class": "ConnectionPoint",
        "Labels": "{\"local_name\": \"TwentyFiveGigE0/0/0/18/0\", \"mac\": \"7c:f8:80:8e:4d:4c\"}",
        "id": "1006",
        "Capacities": "{\"bw\": 25}",
        "StitchNode": "false",
        "Name": "TwentyFiveGigE0/0/0/18/0"
      },
      "elementId": "8738"
    }
  },
  {
    "cp": {
      "identity": 8740,
      "labels": [
        "ConnectionPoint",
        "GraphNode"
      ],
      "properties": {
        "LabelDelegations": "{\"609048fb-8416-463d-9f79-c3671cec197e\": {\"pool_id\": \"_\", \"labels\": {\"mac\": \"7c:f8:80:8e:4d:4d\", \"local_name\": \"TwentyFiveGigE0/0/0/18/1\"}}}",
        "Type": "TrunkPort",
        "GraphID": "40df44eb-1e69-409b-9f46-c3a975338659",
        "CapacityDelegations": "{\"609048fb-8416-463d-9f79-c3671cec197e\": {\"pool_id\": \"_\", \"capacities\": {\"bw\": 25}}}",
        "StructuralInfo": "{\"adm_graph_ids\": [\"609048fb-8416-463d-9f79-c3671cec197e\", \"992f4a14-8005-445f-ad9a-07db92cc5366\"]}",
        "NodeID": "port+ucsd-data-sw:TwentyFiveGigE0/0/0/18/1",
        "Class": "ConnectionPoint",
        "Labels": "{\"local_name\": \"TwentyFiveGigE0/0/0/18/1\", \"mac\": \"7c:f8:80:8e:4d:4d\"}",
        "id": "1007",
        "Capacities": "{\"bw\": 25}",
        "StitchNode": "false",
        "Name": "TwentyFiveGigE0/0/0/18/1"
      },
      "elementId": "8740"
    }
  },
  {
    "cp": {
      "identity": 8612,
      "labels": [
        "ConnectionPoint",
        "GraphNode"
      ],
      "properties": {
        "LabelDelegations": "{\"609048fb-8416-463d-9f79-c3671cec197e\": {\"pool_id\": \"_\", \"labels\": {\"mac\": \"7c:f8:80:8e:4d:04\", \"local_name\": \"HundredGigE0/0/0/0\"}}}",
        "Type": "TrunkPort",
        "GraphID": "40df44eb-1e69-409b-9f46-c3a975338659",
        "CapacityDelegations": "{\"609048fb-8416-463d-9f79-c3671cec197e\": {\"pool_id\": \"_\", \"capacities\": {\"bw\": 100}}}",
        "StructuralInfo": "{\"adm_graph_ids\": [\"609048fb-8416-463d-9f79-c3671cec197e\", \"992f4a14-8005-445f-ad9a-07db92cc5366\"]}",
        "NodeID": "port+ucsd-data-sw:HundredGigE0/0/0/0",
        "Class": "ConnectionPoint",
        "Labels": "{\"local_name\": \"HundredGigE0/0/0/0\", \"mac\": \"7c:f8:80:8e:4d:04\"}",
        "id": "989",
        "Capacities": "{\"bw\": 100}",
        "StitchNode": "false",
        "Name": "HundredGigE0/0/0/0"
      },
      "elementId": "8612"
    }
  },
  {
    "cp": {
      "identity": 9292,
      "labels": [
        "ConnectionPoint",
        "GraphNode"
      ],
      "properties": {
        "Type": "TrunkPort",
        "GraphID": "40df44eb-1e69-409b-9f46-c3a975338659",
        "StructuralInfo": "{\"adm_graph_ids\": [\"992f4a14-8005-445f-ad9a-07db92cc5366\"]}",
        "NodeID": "port+ucsd-data-sw:HundredGigE0/0/0/25/3",
        "Class": "ConnectionPoint",
        "id": "141",
        "StitchNode": "false",
        "Name": "HundredGigE0/0/0/25/3"
      },
      "elementId": "9292"
    }
  },
  {
    "cp": {
      "identity": 9282,
      "labels": [
        "ConnectionPoint",
        "GraphNode"
      ],
      "properties": {
        "Type": "TrunkPort",
        "GraphID": "40df44eb-1e69-409b-9f46-c3a975338659",
        "StructuralInfo": "{\"adm_graph_ids\": [\"992f4a14-8005-445f-ad9a-07db92cc5366\"]}",
        "NodeID": "port+ucsd-data-sw:HundredGigE0/0/0/25/0",
        "Class": "ConnectionPoint",
        "id": "135",
        "StitchNode": "false",
        "Name": "HundredGigE0/0/0/25/0"
      },
      "elementId": "9282"
    }
  },
  {
    "cp": {
      "identity": 8744,
      "labels": [
        "ConnectionPoint",
        "GraphNode"
      ],
      "properties": {
        "LabelDelegations": "{\"609048fb-8416-463d-9f79-c3671cec197e\": {\"pool_id\": \"_\", \"labels\": {\"mac\": \"7c:f8:80:8e:4d:4f\", \"local_name\": \"TwentyFiveGigE0/0/0/18/3\"}}}",
        "Type": "TrunkPort",
        "GraphID": "40df44eb-1e69-409b-9f46-c3a975338659",
        "CapacityDelegations": "{\"609048fb-8416-463d-9f79-c3671cec197e\": {\"pool_id\": \"_\", \"capacities\": {\"bw\": 25}}}",
        "StructuralInfo": "{\"adm_graph_ids\": [\"609048fb-8416-463d-9f79-c3671cec197e\", \"992f4a14-8005-445f-ad9a-07db92cc5366\"]}",
        "NodeID": "port+ucsd-data-sw:TwentyFiveGigE0/0/0/18/3",
        "Class": "ConnectionPoint",
        "Labels": "{\"local_name\": \"TwentyFiveGigE0/0/0/18/3\", \"mac\": \"7c:f8:80:8e:4d:4f\"}",
        "id": "1009",
        "Capacities": "{\"bw\": 25}",
        "StitchNode": "false",
        "Name": "TwentyFiveGigE0/0/0/18/3"
      },
      "elementId": "8744"
    }
  },
  {
    "cp": {
      "identity": 8631,
      "labels": [
        "ConnectionPoint",
        "GraphNode"
      ],
      "properties": {
        "LabelDelegations": "{\"609048fb-8416-463d-9f79-c3671cec197e\": {\"pool_id\": \"_\", \"labels\": {\"mac\": \"7c:f8:80:8e:4d:1c\", \"local_name\": \"HundredGigE0/0/0/6\"}}}",
        "Type": "TrunkPort",
        "GraphID": "40df44eb-1e69-409b-9f46-c3a975338659",
        "CapacityDelegations": "{\"609048fb-8416-463d-9f79-c3671cec197e\": {\"pool_id\": \"_\", \"capacities\": {\"bw\": 100}}}",
        "StructuralInfo": "{\"adm_graph_ids\": [\"609048fb-8416-463d-9f79-c3671cec197e\", \"992f4a14-8005-445f-ad9a-07db92cc5366\"]}",
        "NodeID": "port+ucsd-data-sw:HundredGigE0/0/0/6",
        "Class": "ConnectionPoint",
        "Labels": "{\"local_name\": \"HundredGigE0/0/0/6\", \"mac\": \"7c:f8:80:8e:4d:1c\"}",
        "id": "998",
        "Capacities": "{\"bw\": 100}",
        "StitchNode": "false",
        "Name": "HundredGigE0/0/0/6"
      },
      "elementId": "8631"
    }
  },
  {
    "cp": {
      "identity": 8634,
      "labels": [
        "ConnectionPoint",
        "GraphNode"
      ],
      "properties": {
        "LabelDelegations": "{\"609048fb-8416-463d-9f79-c3671cec197e\": {\"pool_id\": \"_\", \"labels\": {\"mac\": \"7c:f8:80:8e:4d:20\", \"local_name\": \"HundredGigE0/0/0/7\"}}}",
        "Type": "TrunkPort",
        "GraphID": "40df44eb-1e69-409b-9f46-c3a975338659",
        "CapacityDelegations": "{\"609048fb-8416-463d-9f79-c3671cec197e\": {\"pool_id\": \"_\", \"capacities\": {\"bw\": 100}}}",
        "StructuralInfo": "{\"adm_graph_ids\": [\"609048fb-8416-463d-9f79-c3671cec197e\", \"992f4a14-8005-445f-ad9a-07db92cc5366\"]}",
        "NodeID": "port+ucsd-data-sw:HundredGigE0/0/0/7",
        "Class": "ConnectionPoint",
        "Labels": "{\"local_name\": \"HundredGigE0/0/0/7\", \"mac\": \"7c:f8:80:8e:4d:20\"}",
        "id": "999",
        "Capacities": "{\"bw\": 100}",
        "StitchNode": "false",
        "Name": "HundredGigE0/0/0/7"
      },
      "elementId": "8634"
    }
  },
  {
    "cp": {
      "identity": 8735,
      "labels": [
        "ConnectionPoint",
        "GraphNode"
      ],
      "properties": {
        "LabelDelegations": "{\"609048fb-8416-463d-9f79-c3671cec197e\": {\"pool_id\": \"_\", \"labels\": {\"mac\": \"7c:f8:80:8e:4d:46\", \"local_name\": \"TwentyFiveGigE0/0/0/16/2\"}}}",
        "Type": "TrunkPort",
        "GraphID": "40df44eb-1e69-409b-9f46-c3a975338659",
        "CapacityDelegations": "{\"609048fb-8416-463d-9f79-c3671cec197e\": {\"pool_id\": \"_\", \"capacities\": {\"bw\": 25}}}",
        "StructuralInfo": "{\"adm_graph_ids\": [\"609048fb-8416-463d-9f79-c3671cec197e\", \"992f4a14-8005-445f-ad9a-07db92cc5366\"]}",
        "NodeID": "port+ucsd-data-sw:TwentyFiveGigE0/0/0/16/2",
        "Class": "ConnectionPoint",
        "Labels": "{\"local_name\": \"TwentyFiveGigE0/0/0/16/2\", \"mac\": \"7c:f8:80:8e:4d:46\"}",
        "id": "1004",
        "Capacities": "{\"bw\": 25}",
        "StitchNode": "false",
        "Name": "TwentyFiveGigE0/0/0/16/2"
      },
      "elementId": "8735"
    }
  },
  {
    "cp": {
      "identity": 8741,
      "labels": [
        "ConnectionPoint",
        "GraphNode"
      ],
      "properties": {
        "LabelDelegations": "{\"609048fb-8416-463d-9f79-c3671cec197e\": {\"pool_id\": \"_\", \"labels\": {\"mac\": \"7c:f8:80:8e:4d:4e\", \"local_name\": \"TwentyFiveGigE0/0/0/18/2\"}}}",
        "Type": "TrunkPort",
        "GraphID": "40df44eb-1e69-409b-9f46-c3a975338659",
        "CapacityDelegations": "{\"609048fb-8416-463d-9f79-c3671cec197e\": {\"pool_id\": \"_\", \"capacities\": {\"bw\": 25}}}",
        "StructuralInfo": "{\"adm_graph_ids\": [\"609048fb-8416-463d-9f79-c3671cec197e\", \"992f4a14-8005-445f-ad9a-07db92cc5366\"]}",
        "NodeID": "port+ucsd-data-sw:TwentyFiveGigE0/0/0/18/2",
        "Class": "ConnectionPoint",
        "Labels": "{\"local_name\": \"TwentyFiveGigE0/0/0/18/2\", \"mac\": \"7c:f8:80:8e:4d:4e\"}",
        "id": "1008",
        "Capacities": "{\"bw\": 25}",
        "StitchNode": "false",
        "Name": "TwentyFiveGigE0/0/0/18/2"
      },
      "elementId": "8741"
    }
  },
  {
    "cp": {
      "identity": 8627,
      "labels": [
        "ConnectionPoint",
        "GraphNode"
      ],
      "properties": {
        "LabelDelegations": "{\"609048fb-8416-463d-9f79-c3671cec197e\": {\"pool_id\": \"_\", \"labels\": {\"mac\": \"7c:f8:80:8e:4d:14\", \"local_name\": \"HundredGigE0/0/0/4\"}}}",
        "Type": "TrunkPort",
        "GraphID": "40df44eb-1e69-409b-9f46-c3a975338659",
        "CapacityDelegations": "{\"609048fb-8416-463d-9f79-c3671cec197e\": {\"pool_id\": \"_\", \"capacities\": {\"bw\": 100}}}",
        "StructuralInfo": "{\"adm_graph_ids\": [\"609048fb-8416-463d-9f79-c3671cec197e\", \"992f4a14-8005-445f-ad9a-07db92cc5366\"]}",
        "NodeID": "port+ucsd-data-sw:HundredGigE0/0/0/4",
        "Class": "ConnectionPoint",
        "Labels": "{\"local_name\": \"HundredGigE0/0/0/4\", \"mac\": \"7c:f8:80:8e:4d:14\"}",
        "id": "996",
        "Capacities": "{\"bw\": 100}",
        "StitchNode": "false",
        "Name": "HundredGigE0/0/0/4"
      },
      "elementId": "8627"
    }
  },
  {
    "cp": {
      "identity": 8629,
      "labels": [
        "ConnectionPoint",
        "GraphNode"
      ],
      "properties": {
        "LabelDelegations": "{\"609048fb-8416-463d-9f79-c3671cec197e\": {\"pool_id\": \"_\", \"labels\": {\"mac\": \"7c:f8:80:8e:4d:18\", \"local_name\": \"HundredGigE0/0/0/5\"}}}",
        "Type": "TrunkPort",
        "GraphID": "40df44eb-1e69-409b-9f46-c3a975338659",
        "CapacityDelegations": "{\"609048fb-8416-463d-9f79-c3671cec197e\": {\"pool_id\": \"_\", \"capacities\": {\"bw\": 100}}}",
        "StructuralInfo": "{\"adm_graph_ids\": [\"609048fb-8416-463d-9f79-c3671cec197e\", \"992f4a14-8005-445f-ad9a-07db92cc5366\"]}",
        "NodeID": "port+ucsd-data-sw:HundredGigE0/0/0/5",
        "Class": "ConnectionPoint",
        "Labels": "{\"local_name\": \"HundredGigE0/0/0/5\", \"mac\": \"7c:f8:80:8e:4d:18\"}",
        "id": "997",
        "Capacities": "{\"bw\": 100}",
        "StitchNode": "false",
        "Name": "HundredGigE0/0/0/5"
      },
      "elementId": "8629"
    }
  },
  {
    "cp": {
      "identity": 9266,
      "labels": [
        "ConnectionPoint",
        "GraphNode"
      ],
      "properties": {
        "LabelDelegations": "{\"992f4a14-8005-445f-ad9a-07db92cc5366\": {\"pool_id\": \"_\", \"labels\": {\"local_name\": \"p3\"}}}",
        "Type": "DedicatedPort",
        "GraphID": "40df44eb-1e69-409b-9f46-c3a975338659",
        "CapacityDelegations": "{\"992f4a14-8005-445f-ad9a-07db92cc5366\": {\"pool_id\": \"_\", \"capacities\": {\"bw\": 100}}}",
        "StructuralInfo": "{\"adm_graph_ids\": [\"992f4a14-8005-445f-ad9a-07db92cc5366\"]}",
        "NodeID": "node+ucsd-p4-sw:ip+192.168.24.7-int3",
        "Labels": "{\"local_name\": \"p3\"}",
        "Class": "ConnectionPoint",
        "id": "120",
        "Capacities": "{\"bw\": 100}",
        "StitchNode": "false",
        "Name": "p3"
      },
      "elementId": "9266"
    }
  },
  {
    "cp": {
      "identity": 9264,
      "labels": [
        "ConnectionPoint",
        "GraphNode"
      ],
      "properties": {
        "LabelDelegations": "{\"992f4a14-8005-445f-ad9a-07db92cc5366\": {\"pool_id\": \"_\", \"labels\": {\"local_name\": \"p1\"}}}",
        "Type": "DedicatedPort",
        "GraphID": "40df44eb-1e69-409b-9f46-c3a975338659",
        "CapacityDelegations": "{\"992f4a14-8005-445f-ad9a-07db92cc5366\": {\"pool_id\": \"_\", \"capacities\": {\"bw\": 100}}}",
        "StructuralInfo": "{\"adm_graph_ids\": [\"992f4a14-8005-445f-ad9a-07db92cc5366\"]}",
        "NodeID": "node+ucsd-p4-sw:ip+192.168.24.7-int1",
        "Labels": "{\"local_name\": \"p1\"}",
        "Class": "ConnectionPoint",
        "id": "118",
        "Capacities": "{\"bw\": 100}",
        "StitchNode": "false",
        "Name": "p1"
      },
      "elementId": "9264"
    }
  },
  {
    "cp": {
      "identity": 9270,
      "labels": [
        "ConnectionPoint",
        "GraphNode"
      ],
      "properties": {
        "LabelDelegations": "{\"992f4a14-8005-445f-ad9a-07db92cc5366\": {\"pool_id\": \"_\", \"labels\": {\"local_name\": \"p6\"}}}",
        "Type": "DedicatedPort",
        "GraphID": "40df44eb-1e69-409b-9f46-c3a975338659",
        "CapacityDelegations": "{\"992f4a14-8005-445f-ad9a-07db92cc5366\": {\"pool_id\": \"_\", \"capacities\": {\"bw\": 100}}}",
        "StructuralInfo": "{\"adm_graph_ids\": [\"992f4a14-8005-445f-ad9a-07db92cc5366\"]}",
        "NodeID": "node+ucsd-p4-sw:ip+192.168.24.7-int6",
        "Labels": "{\"local_name\": \"p6\"}",
        "Class": "ConnectionPoint",
        "id": "123",
        "Capacities": "{\"bw\": 100}",
        "StitchNode": "false",
        "Name": "p6"
      },
      "elementId": "9270"
    }
  },
  {
    "cp": {
      "identity": 9265,
      "labels": [
        "ConnectionPoint",
        "GraphNode"
      ],
      "properties": {
        "LabelDelegations": "{\"992f4a14-8005-445f-ad9a-07db92cc5366\": {\"pool_id\": \"_\", \"labels\": {\"local_name\": \"p2\"}}}",
        "Type": "DedicatedPort",
        "GraphID": "40df44eb-1e69-409b-9f46-c3a975338659",
        "StructuralInfo": "{\"adm_graph_ids\": [\"992f4a14-8005-445f-ad9a-07db92cc5366\"]}",
        "NodeID": "node+ucsd-p4-sw:ip+192.168.24.7-int2",
        "Labels": "{\"local_name\": \"p2\"}",
        "Class": "ConnectionPoint",
        "id": "119",
        "StitchNode": "false",
        "Name": "p2"
      },
      "elementId": "9265"
    }
  },
  {
    "cp": {
      "identity": 9271,
      "labels": [
        "ConnectionPoint",
        "GraphNode"
      ],
      "properties": {
        "LabelDelegations": "{\"992f4a14-8005-445f-ad9a-07db92cc5366\": {\"pool_id\": \"_\", \"labels\": {\"local_name\": \"p7\"}}}",
        "Type": "DedicatedPort",
        "GraphID": "40df44eb-1e69-409b-9f46-c3a975338659",
        "CapacityDelegations": "{\"992f4a14-8005-445f-ad9a-07db92cc5366\": {\"pool_id\": \"_\", \"capacities\": {\"bw\": 100}}}",
        "StructuralInfo": "{\"adm_graph_ids\": [\"992f4a14-8005-445f-ad9a-07db92cc5366\"]}",
        "NodeID": "node+ucsd-p4-sw:ip+192.168.24.7-int7",
        "Labels": "{\"local_name\": \"p7\"}",
        "Class": "ConnectionPoint",
        "id": "124",
        "Capacities": "{\"bw\": 100}",
        "StitchNode": "false",
        "Name": "p7"
      },
      "elementId": "9271"
    }
  },
  {
    "cp": {
      "identity": 9268,
      "labels": [
        "ConnectionPoint",
        "GraphNode"
      ],
      "properties": {
        "LabelDelegations": "{\"992f4a14-8005-445f-ad9a-07db92cc5366\": {\"pool_id\": \"_\", \"labels\": {\"local_name\": \"p4\"}}}",
        "Type": "DedicatedPort",
        "GraphID": "40df44eb-1e69-409b-9f46-c3a975338659",
        "CapacityDelegations": "{\"992f4a14-8005-445f-ad9a-07db92cc5366\": {\"pool_id\": \"_\", \"capacities\": {\"bw\": 100}}}",
        "StructuralInfo": "{\"adm_graph_ids\": [\"992f4a14-8005-445f-ad9a-07db92cc5366\"]}",
        "NodeID": "node+ucsd-p4-sw:ip+192.168.24.7-int4",
        "Labels": "{\"local_name\": \"p4\"}",
        "Class": "ConnectionPoint",
        "id": "121",
        "Capacities": "{\"bw\": 100}",
        "StitchNode": "false",
        "Name": "p4"
      },
      "elementId": "9268"
    }
  },
  {
    "cp": {
      "identity": 9272,
      "labels": [
        "ConnectionPoint",
        "GraphNode"
      ],
      "properties": {
        "LabelDelegations": "{\"992f4a14-8005-445f-ad9a-07db92cc5366\": {\"pool_id\": \"_\", \"labels\": {\"local_name\": \"p8\"}}}",
        "Type": "DedicatedPort",
        "GraphID": "40df44eb-1e69-409b-9f46-c3a975338659",
        "CapacityDelegations": "{\"992f4a14-8005-445f-ad9a-07db92cc5366\": {\"pool_id\": \"_\", \"capacities\": {\"bw\": 100}}}",
        "StructuralInfo": "{\"adm_graph_ids\": [\"992f4a14-8005-445f-ad9a-07db92cc5366\"]}",
        "NodeID": "node+ucsd-p4-sw:ip+192.168.24.7-int8",
        "Labels": "{\"local_name\": \"p8\"}",
        "Class": "ConnectionPoint",
        "id": "125",
        "Capacities": "{\"bw\": 100}",
        "StitchNode": "false",
        "Name": "p8"
      },
      "elementId": "9272"
    }
  },
  {
    "cp": {
      "identity": 9269,
      "labels": [
        "ConnectionPoint",
        "GraphNode"
      ],
      "properties": {
        "LabelDelegations": "{\"992f4a14-8005-445f-ad9a-07db92cc5366\": {\"pool_id\": \"_\", \"labels\": {\"local_name\": \"p5\"}}}",
        "Type": "DedicatedPort",
        "GraphID": "40df44eb-1e69-409b-9f46-c3a975338659",
        "CapacityDelegations": "{\"992f4a14-8005-445f-ad9a-07db92cc5366\": {\"pool_id\": \"_\", \"capacities\": {\"bw\": 100}}}",
        "StructuralInfo": "{\"adm_graph_ids\": [\"992f4a14-8005-445f-ad9a-07db92cc5366\"]}",
        "NodeID": "node+ucsd-p4-sw:ip+192.168.24.7-int5",
        "Labels": "{\"local_name\": \"p5\"}",
        "Class": "ConnectionPoint",
        "id": "122",
        "Capacities": "{\"bw\": 100}",
        "StitchNode": "false",
        "Name": "p5"
      },
      "elementId": "9269"
    }
  }
]